{
  "tileId": "root-nw-ne",
  "level": 1,
  "parentTileId": "root-nw",
  "childTileIds": [
    "root-nw-ne-nw",
    "root-nw-ne-ne",
    "root-nw-ne-sw",
    "root-nw-ne-se"
  ],
  "bounds": {
    "raMinDeg": 90.0,
    "raMaxDeg": 180,
    "decMinDeg": 45.0,
    "decMaxDeg": 90
  },
  "magMin": 1.81,
  "magMax": 6.5,
  "starCount": 266,
  "stars": [
    {
      "id": "hip-54061",
      "sourceId": "HIP 54061",
      "raDeg": 165.932654,
      "decDeg": 61.751119,
      "pmRaMasYr": -136.46,
      "pmDecMasYr": -35.25,
      "parallaxMas": 26.38,
      "mag": 1.81,
      "colorIndex": 1.061,
      "tier": "T0"
    },
    {
      "id": "hip-53910",
      "sourceId": "HIP 53910",
      "raDeg": 165.459961,
      "decDeg": 56.382345,
      "pmRaMasYr": 81.66,
      "pmDecMasYr": 33.74,
      "parallaxMas": 41.07,
      "mag": 2.34,
      "colorIndex": 0.033,
      "tier": "T0"
    },
    {
      "id": "hip-58001",
      "sourceId": "HIP 58001",
      "raDeg": 178.457255,
      "decDeg": 53.694733,
      "pmRaMasYr": 107.76,
      "pmDecMasYr": 11.16,
      "parallaxMas": 38.99,
      "mag": 2.41,
      "colorIndex": 0.044,
      "tier": "T0"
    },
    {
      "id": "hip-44127",
      "sourceId": "HIP 44127",
      "raDeg": 134.803495,
      "decDeg": 48.04235,
      "pmRaMasYr": -441.12,
      "pmDecMasYr": -215.21,
      "parallaxMas": 68.32,
      "mag": 3.12,
      "colorIndex": 0.223,
      "tier": "T1"
    },
    {
      "id": "hip-46853",
      "sourceId": "HIP 46853",
      "raDeg": 143.218022,
      "decDeg": 51.678602,
      "pmRaMasYr": -947.06,
      "pmDecMasYr": -535.6,
      "parallaxMas": 74.15,
      "mag": 3.17,
      "colorIndex": 0.475,
      "tier": "T1"
    },
    {
      "id": "hip-41704",
      "sourceId": "HIP 41704",
      "raDeg": 127.566792,
      "decDeg": 60.718431,
      "pmRaMasYr": -134.31,
      "pmDecMasYr": -107.73,
      "parallaxMas": 17.76,
      "mag": 3.35,
      "colorIndex": 0.856,
      "tier": "T1"
    },
    {
      "id": "hip-44471",
      "sourceId": "HIP 44471",
      "raDeg": 135.906495,
      "decDeg": 47.156659,
      "pmRaMasYr": -37.37,
      "pmDecMasYr": -55.39,
      "parallaxMas": 7.71,
      "mag": 3.57,
      "colorIndex": 0.007,
      "tier": "T1"
    },
    {
      "id": "hip-46733",
      "sourceId": "HIP 46733",
      "raDeg": 142.88154,
      "decDeg": 63.061795,
      "pmRaMasYr": 107.55,
      "pmDecMasYr": 26.86,
      "parallaxMas": 43.2,
      "mag": 3.65,
      "colorIndex": 0.36,
      "tier": "T1"
    },
    {
      "id": "hip-57399",
      "sourceId": "HIP 57399",
      "raDeg": 176.513059,
      "decDeg": 47.779337,
      "pmRaMasYr": -138.38,
      "pmDecMasYr": 28.37,
      "parallaxMas": 16.64,
      "mag": 3.69,
      "colorIndex": 1.181,
      "tier": "T1"
    },
    {
      "id": "hip-48319",
      "sourceId": "HIP 48319",
      "raDeg": 147.748715,
      "decDeg": 59.039104,
      "pmRaMasYr": -294.45,
      "pmDecMasYr": -151.75,
      "parallaxMas": 28.35,
      "mag": 3.78,
      "colorIndex": 0.291,
      "tier": "T1"
    },
    {
      "id": "hip-56211",
      "sourceId": "HIP 56211",
      "raDeg": 172.851202,
      "decDeg": 69.331122,
      "pmRaMasYr": -41.14,
      "pmDecMasYr": -18.79,
      "parallaxMas": 9.76,
      "mag": 3.82,
      "colorIndex": 1.613,
      "tier": "T1"
    },
    {
      "id": "hip-47193",
      "sourceId": "HIP 47193",
      "raDeg": 144.2723,
      "decDeg": 81.326421,
      "pmRaMasYr": -16.77,
      "pmDecMasYr": -15.95,
      "parallaxMas": 3.03,
      "mag": 4.28,
      "colorIndex": 1.488,
      "tier": "T1"
    },
    {
      "id": "hip-33449",
      "sourceId": "HIP 33449",
      "raDeg": 104.319161,
      "decDeg": 58.42306,
      "pmRaMasYr": 6.58,
      "pmDecMasYr": -123.53,
      "parallaxMas": 19.14,
      "mag": 4.35,
      "colorIndex": 0.85,
      "tier": "T1"
    },
    {
      "id": "hip-30060",
      "sourceId": "HIP 30060",
      "raDeg": 94.905795,
      "decDeg": 59.010905,
      "pmRaMasYr": -3.51,
      "pmDecMasYr": 24.43,
      "parallaxMas": 21.88,
      "mag": 4.44,
      "colorIndex": 0.032,
      "tier": "T1"
    },
    {
      "id": "hip-44901",
      "sourceId": "HIP 44901",
      "raDeg": 137.218274,
      "decDeg": 51.604727,
      "pmRaMasYr": -137.81,
      "pmDecMasYr": -32.48,
      "parallaxMas": 34.12,
      "mag": 4.46,
      "colorIndex": 0.288,
      "tier": "T1"
    },
    {
      "id": "hip-47006",
      "sourceId": "HIP 47006",
      "raDeg": 143.706229,
      "decDeg": 52.051568,
      "pmRaMasYr": -65.07,
      "pmDecMasYr": -37.3,
      "parallaxMas": 12.21,
      "mag": 4.47,
      "colorIndex": 0.027,
      "tier": "T1"
    },
    {
      "id": "hip-46977",
      "sourceId": "HIP 46977",
      "raDeg": 143.620699,
      "decDeg": 69.830154,
      "pmRaMasYr": -63.9,
      "pmDecMasYr": 77.59,
      "parallaxMas": 30.89,
      "mag": 4.54,
      "colorIndex": 0.781,
      "tier": "T1"
    },
    {
      "id": "hip-33694",
      "sourceId": "HIP 33694",
      "raDeg": 105.016033,
      "decDeg": 76.977442,
      "pmRaMasYr": 73.18,
      "pmDecMasYr": -13.88,
      "parallaxMas": 17.43,
      "mag": 4.55,
      "colorIndex": 1.365,
      "tier": "T1"
    },
    {
      "id": "hip-48402",
      "sourceId": "HIP 48402",
      "raDeg": 148.026501,
      "decDeg": 54.064286,
      "pmRaMasYr": -4.21,
      "pmDecMasYr": 19.18,
      "parallaxMas": 7.47,
      "mag": 4.55,
      "colorIndex": 0.038,
      "tier": "T1"
    },
    {
      "id": "hip-42527",
      "sourceId": "HIP 42527",
      "raDeg": 130.053744,
      "decDeg": 64.327872,
      "pmRaMasYr": -59.42,
      "pmDecMasYr": 26.44,
      "parallaxMas": 12.92,
      "mag": 4.59,
      "colorIndex": 1.179,
      "tier": "T1"
    },
    {
      "id": "hip-36145",
      "sourceId": "HIP 36145",
      "raDeg": 111.678587,
      "decDeg": 49.211645,
      "pmRaMasYr": -10.79,
      "pmDecMasYr": -48.57,
      "parallaxMas": 13.11,
      "mag": 4.61,
      "colorIndex": -0.001,
      "tier": "T1"
    },
    {
      "id": "hip-45075",
      "sourceId": "HIP 45075",
      "raDeg": 137.72888,
      "decDeg": 63.513781,
      "pmRaMasYr": 99.16,
      "pmDecMasYr": -60.96,
      "parallaxMas": 26.79,
      "mag": 4.67,
      "colorIndex": 0.381,
      "tier": "T1"
    },
    {
      "id": "hip-44390",
      "sourceId": "HIP 44390",
      "raDeg": 135.636358,
      "decDeg": 67.629575,
      "pmRaMasYr": -22.08,
      "pmDecMasYr": 18.15,
      "parallaxMas": 11.35,
      "mag": 4.74,
      "colorIndex": 1.542,
      "tier": "T1"
    },
    {
      "id": "hip-29997",
      "sourceId": "HIP 29997",
      "raDeg": 94.711583,
      "decDeg": 69.320034,
      "pmRaMasYr": -1.64,
      "pmDecMasYr": -101.65,
      "parallaxMas": 18.55,
      "mag": 4.76,
      "colorIndex": 0.025,
      "tier": "T1"
    },
    {
      "id": "hip-39847",
      "sourceId": "HIP 39847",
      "raDeg": 122.114598,
      "decDeg": 51.506676,
      "pmRaMasYr": -60.1,
      "pmDecMasYr": -2.15,
      "parallaxMas": 14.96,
      "mag": 4.78,
      "colorIndex": 0.048,
      "tier": "T1"
    },
    {
      "id": "hip-45038",
      "sourceId": "HIP 45038",
      "raDeg": 137.598026,
      "decDeg": 67.134239,
      "pmRaMasYr": 12.88,
      "pmDecMasYr": -90.85,
      "parallaxMas": 48.87,
      "mag": 4.8,
      "colorIndex": 0.489,
      "tier": "T1"
    },
    {
      "id": "hip-45493",
      "sourceId": "HIP 45493",
      "raDeg": 139.046995,
      "decDeg": 54.021712,
      "pmRaMasYr": 49.14,
      "pmDecMasYr": 59.79,
      "parallaxMas": 27.55,
      "mag": 4.8,
      "colorIndex": 0.199,
      "tier": "T1"
    },
    {
      "id": "hip-51459",
      "sourceId": "HIP 51459",
      "raDeg": 157.657351,
      "decDeg": 55.980618,
      "pmRaMasYr": -177.02,
      "pmDecMasYr": -33.45,
      "parallaxMas": 77.82,
      "mag": 4.82,
      "colorIndex": 0.541,
      "tier": "T1"
    },
    {
      "id": "hip-32438",
      "sourceId": "HIP 32438",
      "raDeg": 101.55897,
      "decDeg": 59.441691,
      "pmRaMasYr": -18.11,
      "pmDecMasYr": -8.67,
      "parallaxMas": 14.26,
      "mag": 4.86,
      "colorIndex": 0.084,
      "tier": "T1"
    },
    {
      "id": "hip-51808",
      "sourceId": "HIP 51808",
      "raDeg": 158.773285,
      "decDeg": 75.712984,
      "pmRaMasYr": -45.58,
      "pmDecMasYr": -14.96,
      "parallaxMas": 12.68,
      "mag": 4.86,
      "colorIndex": 0.957,
      "tier": "T1"
    },
    {
      "id": "hip-33485",
      "sourceId": "HIP 33485",
      "raDeg": 104.404687,
      "decDeg": 45.094102,
      "pmRaMasYr": -21.67,
      "pmDecMasYr": -3.18,
      "parallaxMas": 14.49,
      "mag": 4.9,
      "colorIndex": 0.027,
      "tier": "T1"
    },
    {
      "id": "hip-30520",
      "sourceId": "HIP 30520",
      "raDeg": 96.224592,
      "decDeg": 49.287899,
      "pmRaMasYr": 0.82,
      "pmDecMasYr": -2.48,
      "parallaxMas": 0.85,
      "mag": 4.92,
      "colorIndex": 1.905,
      "tier": "T1"
    },
    {
      "id": "hip-36547",
      "sourceId": "HIP 36547",
      "raDeg": 112.768668,
      "decDeg": 82.411569,
      "pmRaMasYr": -3.71,
      "pmDecMasYr": -42.31,
      "parallaxMas": 6.89,
      "mag": 4.92,
      "colorIndex": 1.633,
      "tier": "T1"
    },
    {
      "id": "hip-37609",
      "sourceId": "HIP 37609",
      "raDeg": 115.751907,
      "decDeg": 58.710487,
      "pmRaMasYr": -36.99,
      "pmDecMasYr": -52.11,
      "parallaxMas": 13.75,
      "mag": 4.93,
      "colorIndex": 0.104,
      "tier": "T1"
    },
    {
      "id": "hip-50933",
      "sourceId": "HIP 50933",
      "raDeg": 156.032745,
      "decDeg": 65.566474,
      "pmRaMasYr": -8.93,
      "pmDecMasYr": -20.83,
      "parallaxMas": 10.84,
      "mag": 4.94,
      "colorIndex": -0.052,
      "tier": "T1"
    },
    {
      "id": "hip-35384",
      "sourceId": "HIP 35384",
      "raDeg": 109.633246,
      "decDeg": 49.464746,
      "pmRaMasYr": -1.36,
      "pmDecMasYr": 3.91,
      "parallaxMas": 10.97,
      "mag": 5.0,
      "colorIndex": 0.087,
      "tier": "T1"
    },
    {
      "id": "hip-29919",
      "sourceId": "HIP 29919",
      "raDeg": 94.478467,
      "decDeg": 61.515292,
      "pmRaMasYr": -9.61,
      "pmDecMasYr": -2.37,
      "parallaxMas": 5.53,
      "mag": 5.01,
      "colorIndex": 1.843,
      "tier": "T1"
    },
    {
      "id": "hip-52425",
      "sourceId": "HIP 52425",
      "raDeg": 160.766831,
      "decDeg": 69.076245,
      "pmRaMasYr": 0.28,
      "pmDecMasYr": -12.86,
      "parallaxMas": 7.65,
      "mag": 5.01,
      "colorIndex": 1.406,
      "tier": "T1"
    },
    {
      "id": "hip-37391",
      "sourceId": "HIP 37391",
      "raDeg": 115.129548,
      "decDeg": 87.020156,
      "pmRaMasYr": -53.48,
      "pmDecMasYr": -26.85,
      "parallaxMas": 6.53,
      "mag": 5.05,
      "colorIndex": 1.604,
      "tier": "T1"
    },
    {
      "id": "hip-48113",
      "sourceId": "HIP 48113",
      "raDeg": 147.146604,
      "decDeg": 46.021233,
      "pmRaMasYr": 222.07,
      "pmDecMasYr": -92.62,
      "parallaxMas": 54.26,
      "mag": 5.08,
      "colorIndex": 0.619,
      "tier": "T1"
    },
    {
      "id": "hip-47965",
      "sourceId": "HIP 47965",
      "raDeg": 146.631934,
      "decDeg": 57.12799,
      "pmRaMasYr": 0.12,
      "pmDecMasYr": 33.12,
      "parallaxMas": 5.86,
      "mag": 5.09,
      "colorIndex": 1.594,
      "tier": "T1"
    },
    {
      "id": "hip-33104",
      "sourceId": "HIP 33104",
      "raDeg": 103.426005,
      "decDeg": 68.888292,
      "pmRaMasYr": 4.53,
      "pmDecMasYr": 7.3,
      "parallaxMas": 3.26,
      "mag": 5.11,
      "colorIndex": -0.114,
      "tier": "T1"
    },
    {
      "id": "hip-52353",
      "sourceId": "HIP 52353",
      "raDeg": 160.486593,
      "decDeg": 65.716462,
      "pmRaMasYr": -162.71,
      "pmDecMasYr": -75.04,
      "parallaxMas": 14.58,
      "mag": 5.12,
      "colorIndex": 1.207,
      "tier": "T1"
    },
    {
      "id": "hip-53261",
      "sourceId": "HIP 53261",
      "raDeg": 163.393828,
      "decDeg": 54.585152,
      "pmRaMasYr": -66.85,
      "pmDecMasYr": -9.83,
      "parallaxMas": 4.82,
      "mag": 5.12,
      "colorIndex": 1.355,
      "tier": "T1"
    },
    {
      "id": "hip-32864",
      "sourceId": "HIP 32864",
      "raDeg": 102.737867,
      "decDeg": 67.571923,
      "pmRaMasYr": 0.93,
      "pmDecMasYr": 4.58,
      "parallaxMas": 3.76,
      "mag": 5.14,
      "colorIndex": -0.152,
      "tier": "T1"
    },
    {
      "id": "hip-44857",
      "sourceId": "HIP 44857",
      "raDeg": 137.098055,
      "decDeg": 66.873333,
      "pmRaMasYr": -23.01,
      "pmDecMasYr": -40.54,
      "parallaxMas": 6.54,
      "mag": 5.15,
      "colorIndex": 1.514,
      "tier": "T1"
    },
    {
      "id": "hip-47654",
      "sourceId": "HIP 47654",
      "raDeg": 145.738494,
      "decDeg": 72.252685,
      "pmRaMasYr": -26.71,
      "pmDecMasYr": -27.49,
      "parallaxMas": 7.38,
      "mag": 5.15,
      "colorIndex": 1.029,
      "tier": "T1"
    },
    {
      "id": "hip-51814",
      "sourceId": "HIP 51814",
      "raDeg": 158.790093,
      "decDeg": 57.082547,
      "pmRaMasYr": 65.65,
      "pmDecMasYr": 37.11,
      "parallaxMas": 37.8,
      "mag": 5.16,
      "colorIndex": 0.349,
      "tier": "T1"
    },
    {
      "id": "hip-45333",
      "sourceId": "HIP 45333",
      "raDeg": 138.58563,
      "decDeg": 61.423395,
      "pmRaMasYr": -8.67,
      "pmDecMasYr": -31.84,
      "parallaxMas": 51.12,
      "mag": 5.18,
      "colorIndex": 0.605,
      "tier": "T1"
    },
    {
      "id": "hip-52469",
      "sourceId": "HIP 52469",
      "raDeg": 160.887989,
      "decDeg": 46.204038,
      "pmRaMasYr": -268.17,
      "pmDecMasYr": -66.06,
      "parallaxMas": 28.05,
      "mag": 5.18,
      "colorIndex": 0.324,
      "tier": "T1"
    },
    {
      "id": "hip-56583",
      "sourceId": "HIP 56583",
      "raDeg": 174.010899,
      "decDeg": 69.32326,
      "pmRaMasYr": 109.23,
      "pmDecMasYr": -126.4,
      "parallaxMas": 13.49,
      "mag": 5.19,
      "colorIndex": 0.974,
      "tier": "T1"
    },
    {
      "id": "hip-35146",
      "sourceId": "HIP 35146",
      "raDeg": 108.979249,
      "decDeg": 59.638096,
      "pmRaMasYr": -101.07,
      "pmDecMasYr": -258.69,
      "parallaxMas": 16.88,
      "mag": 5.2,
      "colorIndex": 1.081,
      "tier": "T1"
    },
    {
      "id": "hip-30679",
      "sourceId": "HIP 30679",
      "raDeg": 96.703663,
      "decDeg": 58.417413,
      "pmRaMasYr": -5.52,
      "pmDecMasYr": -1.77,
      "parallaxMas": 4.78,
      "mag": 5.21,
      "colorIndex": 1.538,
      "tier": "T1"
    },
    {
      "id": "hip-32562",
      "sourceId": "HIP 32562",
      "raDeg": 101.91492,
      "decDeg": 48.789461,
      "pmRaMasYr": -5.25,
      "pmDecMasYr": 6.4,
      "parallaxMas": 7.69,
      "mag": 5.22,
      "colorIndex": 1.131,
      "tier": "T1"
    },
    {
      "id": "hip-51502",
      "sourceId": "HIP 51502",
      "raDeg": 157.770919,
      "decDeg": 82.558538,
      "pmRaMasYr": -79.21,
      "pmDecMasYr": 20.43,
      "parallaxMas": 46.54,
      "mag": 5.25,
      "colorIndex": 0.399,
      "tier": "T1"
    },
    {
      "id": "hip-48682",
      "sourceId": "HIP 48682",
      "raDeg": 148.92919,
      "decDeg": 49.819795,
      "pmRaMasYr": -3.45,
      "pmDecMasYr": 19.66,
      "parallaxMas": 14.65,
      "mag": 5.27,
      "colorIndex": 0.086,
      "tier": "T1"
    },
    {
      "id": "hip-57477",
      "sourceId": "HIP 57477",
      "raDeg": 176.731703,
      "decDeg": 55.628268,
      "pmRaMasYr": 13.44,
      "pmDecMasYr": -31.92,
      "parallaxMas": 15.8,
      "mag": 5.27,
      "colorIndex": 1.276,
      "tier": "T1"
    },
    {
      "id": "hip-45455",
      "sourceId": "HIP 45455",
      "raDeg": 138.957535,
      "decDeg": 56.741477,
      "pmRaMasYr": -24.81,
      "pmDecMasYr": -29.15,
      "parallaxMas": 4.79,
      "mag": 5.28,
      "colorIndex": 1.568,
      "tier": "T1"
    },
    {
      "id": "hip-37701",
      "sourceId": "HIP 37701",
      "raDeg": 116.017449,
      "decDeg": 50.433861,
      "pmRaMasYr": -9.29,
      "pmDecMasYr": -27.78,
      "parallaxMas": 4.73,
      "mag": 5.31,
      "colorIndex": -0.001,
      "tier": "T1"
    },
    {
      "id": "hip-57111",
      "sourceId": "HIP 57111",
      "raDeg": 175.61845,
      "decDeg": 66.744809,
      "pmRaMasYr": -44.98,
      "pmDecMasYr": 40.17,
      "parallaxMas": 5.07,
      "mag": 5.32,
      "colorIndex": 1.267,
      "tier": "T1"
    },
    {
      "id": "hip-30247",
      "sourceId": "HIP 30247",
      "raDeg": 95.442117,
      "decDeg": 53.452395,
      "pmRaMasYr": 22.24,
      "pmDecMasYr": -88.91,
      "parallaxMas": 17.54,
      "mag": 5.34,
      "colorIndex": 0.448,
      "tier": "T1"
    },
    {
      "id": "hip-32489",
      "sourceId": "HIP 32489",
      "raDeg": 101.706227,
      "decDeg": 57.169271,
      "pmRaMasYr": 13.9,
      "pmDecMasYr": -38.79,
      "parallaxMas": 15.69,
      "mag": 5.34,
      "colorIndex": 0.964,
      "tier": "T1"
    },
    {
      "id": "hip-33048",
      "sourceId": "HIP 33048",
      "raDeg": 103.27109,
      "decDeg": 59.448655,
      "pmRaMasYr": -10.84,
      "pmDecMasYr": -45.93,
      "parallaxMas": 7.4,
      "mag": 5.34,
      "colorIndex": 0.675,
      "tier": "T1"
    },
    {
      "id": "hip-40215",
      "sourceId": "HIP 40215",
      "raDeg": 123.203286,
      "decDeg": 68.474054,
      "pmRaMasYr": -1.05,
      "pmDecMasYr": 7.32,
      "parallaxMas": 3.07,
      "mag": 5.34,
      "colorIndex": 1.037,
      "tier": "T1"
    },
    {
      "id": "hip-29246",
      "sourceId": "HIP 29246",
      "raDeg": 92.495811,
      "decDeg": 58.935649,
      "pmRaMasYr": 17.61,
      "pmDecMasYr": 18.77,
      "parallaxMas": 9.34,
      "mag": 5.35,
      "colorIndex": 1.096,
      "tier": "T1"
    },
    {
      "id": "hip-36439",
      "sourceId": "HIP 36439",
      "raDeg": 112.482736,
      "decDeg": 49.672662,
      "pmRaMasYr": 110.4,
      "pmDecMasYr": -82.01,
      "parallaxMas": 50.25,
      "mag": 5.35,
      "colorIndex": 0.47,
      "tier": "T1"
    },
    {
      "id": "hip-42604",
      "sourceId": "HIP 42604",
      "raDeg": 130.254367,
      "decDeg": 45.833785,
      "pmRaMasYr": 27.19,
      "pmDecMasYr": 92.49,
      "parallaxMas": 18.11,
      "mag": 5.35,
      "colorIndex": 0.993,
      "tier": "T1"
    },
    {
      "id": "hip-29490",
      "sourceId": "HIP 29490",
      "raDeg": 93.21272,
      "decDeg": 65.718499,
      "pmRaMasYr": 7.23,
      "pmDecMasYr": -31.75,
      "parallaxMas": 5.08,
      "mag": 5.36,
      "colorIndex": 1.344,
      "tier": "T1"
    },
    {
      "id": "hip-29730",
      "sourceId": "HIP 29730",
      "raDeg": 93.918782,
      "decDeg": 59.999034,
      "pmRaMasYr": 28.54,
      "pmDecMasYr": -24.14,
      "parallaxMas": 6.54,
      "mag": 5.37,
      "colorIndex": 1.339,
      "tier": "T1"
    },
    {
      "id": "hip-39117",
      "sourceId": "HIP 39117",
      "raDeg": 120.048984,
      "decDeg": 73.91801,
      "pmRaMasYr": -8.43,
      "pmDecMasYr": -37.4,
      "parallaxMas": 4.66,
      "mag": 5.37,
      "colorIndex": 1.424,
      "tier": "T1"
    },
    {
      "id": "hip-39538",
      "sourceId": "HIP 39538",
      "raDeg": 121.196609,
      "decDeg": 79.479743,
      "pmRaMasYr": -36.46,
      "pmDecMasYr": -53.75,
      "parallaxMas": 9.88,
      "mag": 5.39,
      "colorIndex": -0.04,
      "tier": "T1"
    },
    {
      "id": "hip-46471",
      "sourceId": "HIP 46471",
      "raDeg": 142.166644,
      "decDeg": 45.601795,
      "pmRaMasYr": -6.4,
      "pmDecMasYr": -128.2,
      "parallaxMas": 11.33,
      "mag": 5.4,
      "colorIndex": 0.993,
      "tier": "T1"
    },
    {
      "id": "hip-32439",
      "sourceId": "HIP 32439",
      "raDeg": 101.56029,
      "decDeg": 79.566278,
      "pmRaMasYr": -99.03,
      "pmDecMasYr": -603.61,
      "parallaxMas": 56.02,
      "mag": 5.44,
      "colorIndex": 0.525,
      "tier": "T1"
    },
    {
      "id": "hip-34912",
      "sourceId": "HIP 34912",
      "raDeg": 108.347472,
      "decDeg": 51.428712,
      "pmRaMasYr": 8.19,
      "pmDecMasYr": 13.44,
      "parallaxMas": 4.22,
      "mag": 5.46,
      "colorIndex": 1.64,
      "tier": "T1"
    },
    {
      "id": "hip-56290",
      "sourceId": "HIP 56290",
      "raDeg": 173.086487,
      "decDeg": 61.082752,
      "pmRaMasYr": -14.21,
      "pmDecMasYr": -95.13,
      "parallaxMas": 36.34,
      "mag": 5.46,
      "colorIndex": 0.515,
      "tier": "T1"
    },
    {
      "id": "hip-38639",
      "sourceId": "HIP 38639",
      "raDeg": 118.678078,
      "decDeg": 47.564592,
      "pmRaMasYr": -48.4,
      "pmDecMasYr": 1.48,
      "parallaxMas": 6.42,
      "mag": 5.47,
      "colorIndex": 1.462,
      "tier": "T1"
    },
    {
      "id": "hip-42080",
      "sourceId": "HIP 42080",
      "raDeg": 128.65078,
      "decDeg": 65.145273,
      "pmRaMasYr": -47.06,
      "pmDecMasYr": -42.5,
      "parallaxMas": 20.63,
      "mag": 5.47,
      "colorIndex": 0.207,
      "tier": "T1"
    },
    {
      "id": "hip-53781",
      "sourceId": "HIP 53781",
      "raDeg": 165.061234,
      "decDeg": 45.526269,
      "pmRaMasYr": 9.66,
      "pmDecMasYr": 3.03,
      "parallaxMas": 3.7,
      "mag": 5.47,
      "colorIndex": 1.466,
      "tier": "T1"
    },
    {
      "id": "hip-44613",
      "sourceId": "HIP 44613",
      "raDeg": 136.350444,
      "decDeg": 48.530358,
      "pmRaMasYr": -12.03,
      "pmDecMasYr": -18.22,
      "parallaxMas": 9.37,
      "mag": 5.48,
      "colorIndex": 0.475,
      "tier": "T1"
    },
    {
      "id": "hip-49005",
      "sourceId": "HIP 49005",
      "raDeg": 149.9655,
      "decDeg": 56.811876,
      "pmRaMasYr": -31.49,
      "pmDecMasYr": -28.04,
      "parallaxMas": 6.39,
      "mag": 5.5,
      "colorIndex": 1.487,
      "tier": "T1"
    },
    {
      "id": "hip-41152",
      "sourceId": "HIP 41152",
      "raDeg": 125.952205,
      "decDeg": 53.219951,
      "pmRaMasYr": -27.58,
      "pmDecMasYr": -98.39,
      "parallaxMas": 19.46,
      "mag": 5.52,
      "colorIndex": 0.125,
      "tier": "T1"
    },
    {
      "id": "hip-51384",
      "sourceId": "HIP 51384",
      "raDeg": 157.425868,
      "decDeg": 84.252105,
      "pmRaMasYr": -128.39,
      "pmDecMasYr": -39.6,
      "parallaxMas": 24.52,
      "mag": 5.52,
      "colorIndex": 0.244,
      "tier": "T1"
    },
    {
      "id": "hip-30651",
      "sourceId": "HIP 30651",
      "raDeg": 96.607765,
      "decDeg": 56.285044,
      "pmRaMasYr": -25.21,
      "pmDecMasYr": 21.57,
      "parallaxMas": 12.01,
      "mag": 5.53,
      "colorIndex": 0.238,
      "tier": "T1"
    },
    {
      "id": "hip-32609",
      "sourceId": "HIP 32609",
      "raDeg": 102.050968,
      "decDeg": 55.70445,
      "pmRaMasYr": 57.71,
      "pmDecMasYr": -104.75,
      "parallaxMas": 21.26,
      "mag": 5.54,
      "tier": "T1"
    },
    {
      "id": "hip-35136",
      "sourceId": "HIP 35136",
      "raDeg": 108.958805,
      "decDeg": 47.240416,
      "pmRaMasYr": 29.44,
      "pmDecMasYr": -186.12,
      "parallaxMas": 59.31,
      "mag": 5.54,
      "colorIndex": 0.576,
      "tier": "T1"
    },
    {
      "id": "hip-40793",
      "sourceId": "HIP 40793",
      "raDeg": 124.884218,
      "decDeg": 75.756869,
      "pmRaMasYr": 32.28,
      "pmDecMasYr": 15.76,
      "parallaxMas": 11.18,
      "mag": 5.55,
      "colorIndex": 0.902,
      "tier": "T1"
    },
    {
      "id": "hip-52136",
      "sourceId": "HIP 52136",
      "raDeg": 159.773934,
      "decDeg": 53.668493,
      "pmRaMasYr": -90.15,
      "pmDecMasYr": -79.36,
      "parallaxMas": 6.34,
      "mag": 5.55,
      "colorIndex": 1.27,
      "tier": "T1"
    },
    {
      "id": "hip-43903",
      "sourceId": "HIP 43903",
      "raDeg": 134.156195,
      "decDeg": 64.604031,
      "pmRaMasYr": -32.93,
      "pmDecMasYr": -81.88,
      "parallaxMas": 10.59,
      "mag": 5.57,
      "colorIndex": 0.877,
      "tier": "T1"
    },
    {
      "id": "hip-53064",
      "sourceId": "HIP 53064",
      "raDeg": 162.84899,
      "decDeg": 59.320244,
      "pmRaMasYr": -29.73,
      "pmDecMasYr": -51.2,
      "parallaxMas": 12.39,
      "mag": 5.57,
      "colorIndex": 1.16,
      "tier": "T1"
    },
    {
      "id": "hip-37441",
      "sourceId": "HIP 37441",
      "raDeg": 115.301856,
      "decDeg": 48.131852,
      "pmRaMasYr": -52.69,
      "pmDecMasYr": -130.99,
      "parallaxMas": 10.01,
      "mag": 5.58,
      "colorIndex": 1.011,
      "tier": "T1"
    },
    {
      "id": "hip-36528",
      "sourceId": "HIP 36528",
      "raDeg": 112.719581,
      "decDeg": 68.465727,
      "pmRaMasYr": -2.22,
      "pmDecMasYr": -43.68,
      "parallaxMas": 7.2,
      "mag": 5.63,
      "colorIndex": 1.1,
      "tier": "T1"
    },
    {
      "id": "hip-40646",
      "sourceId": "HIP 40646",
      "raDeg": 124.46008,
      "decDeg": 59.571128,
      "pmRaMasYr": -4.22,
      "pmDecMasYr": 1.85,
      "parallaxMas": 10.73,
      "mag": 5.63,
      "colorIndex": 0.182,
      "tier": "T1"
    },
    {
      "id": "hip-42438",
      "sourceId": "HIP 42438",
      "raDeg": 129.798926,
      "decDeg": 65.020693,
      "pmRaMasYr": -27.73,
      "pmDecMasYr": 87.9,
      "parallaxMas": 70.07,
      "mag": 5.63,
      "colorIndex": 0.618,
      "tier": "T1"
    },
    {
      "id": "hip-56510",
      "sourceId": "HIP 56510",
      "raDeg": 173.770404,
      "decDeg": 54.785375,
      "pmRaMasYr": 10.66,
      "pmDecMasYr": 18.02,
      "parallaxMas": 7.94,
      "mag": 5.63,
      "colorIndex": 1.032,
      "tier": "T1"
    },
    {
      "id": "hip-37023",
      "sourceId": "HIP 37023",
      "raDeg": 114.13191,
      "decDeg": 46.180368,
      "pmRaMasYr": -28.39,
      "pmDecMasYr": -32.92,
      "parallaxMas": 6.29,
      "mag": 5.66,
      "colorIndex": 1.56,
      "tier": "T1"
    },
    {
      "id": "hip-42372",
      "sourceId": "HIP 42372",
      "raDeg": 129.592748,
      "decDeg": 53.401575,
      "pmRaMasYr": -76.32,
      "pmDecMasYr": -14.66,
      "parallaxMas": 13.55,
      "mag": 5.66,
      "colorIndex": 0.964,
      "tier": "T1"
    },
    {
      "id": "hip-53043",
      "sourceId": "HIP 53043",
      "raDeg": 162.79618,
      "decDeg": 56.582237,
      "pmRaMasYr": -69.47,
      "pmDecMasYr": 5.46,
      "parallaxMas": 9.32,
      "mag": 5.66,
      "colorIndex": 1.132,
      "tier": "T1"
    },
    {
      "id": "hip-33827",
      "sourceId": "HIP 33827",
      "raDeg": 105.339149,
      "decDeg": 70.808334,
      "pmRaMasYr": 12.75,
      "pmDecMasYr": -15.8,
      "parallaxMas": 7.14,
      "mag": 5.69,
      "colorIndex": 1.337,
      "tier": "T1"
    },
    {
      "id": "hip-36348",
      "sourceId": "HIP 36348",
      "raDeg": 112.214521,
      "decDeg": 48.184038,
      "pmRaMasYr": -3.18,
      "pmDecMasYr": -44.36,
      "parallaxMas": 7.95,
      "mag": 5.7,
      "colorIndex": -0.092,
      "tier": "T1"
    },
    {
      "id": "hip-28499",
      "sourceId": "HIP 28499",
      "raDeg": 90.243995,
      "decDeg": 47.901974,
      "pmRaMasYr": 3.02,
      "pmDecMasYr": -21.03,
      "parallaxMas": 3.19,
      "mag": 5.71,
      "colorIndex": -0.007,
      "tier": "T1"
    },
    {
      "id": "hip-49363",
      "sourceId": "HIP 49363",
      "raDeg": 151.151438,
      "decDeg": 53.891726,
      "pmRaMasYr": -22.58,
      "pmDecMasYr": -3.84,
      "parallaxMas": 21.15,
      "mag": 5.71,
      "colorIndex": 0.507,
      "tier": "T1"
    },
    {
      "id": "hip-43644",
      "sourceId": "HIP 43644",
      "raDeg": 133.344041,
      "decDeg": 61.962214,
      "pmRaMasYr": -9.98,
      "pmDecMasYr": 22.3,
      "parallaxMas": 11.45,
      "mag": 5.72,
      "colorIndex": 0.305,
      "tier": "T1"
    },
    {
      "id": "hip-43923",
      "sourceId": "HIP 43923",
      "raDeg": 134.208572,
      "decDeg": 45.631755,
      "pmRaMasYr": -125.02,
      "pmDecMasYr": -44.75,
      "parallaxMas": 14.21,
      "mag": 5.72,
      "colorIndex": 1.125,
      "tier": "T1"
    },
    {
      "id": "hip-47594",
      "sourceId": "HIP 47594",
      "raDeg": 145.562221,
      "decDeg": 69.237706,
      "pmRaMasYr": -66.55,
      "pmDecMasYr": -69.4,
      "parallaxMas": 6.81,
      "mag": 5.72,
      "colorIndex": 1.131,
      "tier": "T1"
    },
    {
      "id": "hip-40772",
      "sourceId": "HIP 40772",
      "raDeg": 124.821599,
      "decDeg": 62.507139,
      "pmRaMasYr": -20.48,
      "pmDecMasYr": 8.41,
      "parallaxMas": 6.93,
      "mag": 5.73,
      "colorIndex": 0.891,
      "tier": "T1"
    },
    {
      "id": "hip-55797",
      "sourceId": "HIP 55797",
      "raDeg": 171.488268,
      "decDeg": 55.850341,
      "pmRaMasYr": -71.92,
      "pmDecMasYr": 48.81,
      "parallaxMas": 9.38,
      "mag": 5.73,
      "colorIndex": 0.988,
      "tier": "T1"
    },
    {
      "id": "hip-35643",
      "sourceId": "HIP 35643",
      "raDeg": 110.323081,
      "decDeg": 45.22817,
      "pmRaMasYr": -49.53,
      "pmDecMasYr": 12.12,
      "parallaxMas": 28.99,
      "mag": 5.74,
      "colorIndex": 0.342,
      "tier": "T1"
    },
    {
      "id": "hip-44504",
      "sourceId": "HIP 44504",
      "raDeg": 136.001679,
      "decDeg": 54.283877,
      "pmRaMasYr": -1.38,
      "pmDecMasYr": 4.12,
      "parallaxMas": 9.69,
      "mag": 5.74,
      "colorIndex": 0.034,
      "tier": "T1"
    },
    {
      "id": "hip-50448",
      "sourceId": "HIP 50448",
      "raDeg": 154.508961,
      "decDeg": 65.108374,
      "pmRaMasYr": -89.48,
      "pmDecMasYr": -9.28,
      "parallaxMas": 13.07,
      "mag": 5.74,
      "colorIndex": 0.163,
      "tier": "T1"
    },
    {
      "id": "hip-52338",
      "sourceId": "HIP 52338",
      "raDeg": 160.451272,
      "decDeg": 68.44356,
      "pmRaMasYr": -29.43,
      "pmDecMasYr": -24.78,
      "parallaxMas": 5.56,
      "mag": 5.74,
      "colorIndex": 1.315,
      "tier": "T1"
    },
    {
      "id": "hip-31940",
      "sourceId": "HIP 31940",
      "raDeg": 100.120155,
      "decDeg": 77.995797,
      "pmRaMasYr": 14.25,
      "pmDecMasYr": -6.02,
      "parallaxMas": 5.63,
      "mag": 5.75,
      "colorIndex": 1.488,
      "tier": "T1"
    },
    {
      "id": "hip-47013",
      "sourceId": "HIP 47013",
      "raDeg": 143.722453,
      "decDeg": 72.205864,
      "pmRaMasYr": 72.02,
      "pmDecMasYr": -76.06,
      "parallaxMas": 20.06,
      "mag": 5.77,
      "colorIndex": 0.53,
      "tier": "T1"
    },
    {
      "id": "hip-29388",
      "sourceId": "HIP 29388",
      "raDeg": 92.902411,
      "decDeg": 48.711125,
      "pmRaMasYr": 14.3,
      "pmDecMasYr": -55.85,
      "parallaxMas": 10.49,
      "mag": 5.78,
      "colorIndex": 0.1,
      "tier": "T1"
    },
    {
      "id": "hip-39221",
      "sourceId": "HIP 39221",
      "raDeg": 120.336448,
      "decDeg": 59.047318,
      "pmRaMasYr": 25.3,
      "pmDecMasYr": 32.64,
      "parallaxMas": 22.94,
      "mag": 5.78,
      "colorIndex": 0.421,
      "tier": "T1"
    },
    {
      "id": "hip-45915",
      "sourceId": "HIP 45915",
      "raDeg": 140.430418,
      "decDeg": 56.699249,
      "pmRaMasYr": -10.55,
      "pmDecMasYr": -11.91,
      "parallaxMas": 6.84,
      "mag": 5.79,
      "colorIndex": 1.511,
      "tier": "T1"
    },
    {
      "id": "hip-52478",
      "sourceId": "HIP 52478",
      "raDeg": 160.930487,
      "decDeg": 57.199329,
      "pmRaMasYr": 17.38,
      "pmDecMasYr": -51.66,
      "parallaxMas": 8.87,
      "mag": 5.79,
      "colorIndex": -0.038,
      "tier": "T1"
    },
    {
      "id": "hip-35785",
      "sourceId": "HIP 35785",
      "raDeg": 110.716927,
      "decDeg": 55.28147,
      "pmRaMasYr": -11.23,
      "pmDecMasYr": -32.04,
      "parallaxMas": 6.96,
      "mag": 5.8,
      "colorIndex": -0.078,
      "tier": "T1"
    },
    {
      "id": "hip-35984",
      "sourceId": "HIP 35984",
      "raDeg": 111.237828,
      "decDeg": 51.887344,
      "pmRaMasYr": 9.46,
      "pmDecMasYr": -35.14,
      "parallaxMas": 2.84,
      "mag": 5.8,
      "colorIndex": 1.61,
      "tier": "T1"
    },
    {
      "id": "hip-56035",
      "sourceId": "HIP 56035",
      "raDeg": 172.269598,
      "decDeg": 61.777786,
      "pmRaMasYr": -113.93,
      "pmDecMasYr": 239.58,
      "parallaxMas": 30.4,
      "mag": 5.83,
      "colorIndex": 0.382,
      "tier": "T1"
    },
    {
      "id": "hip-58181",
      "sourceId": "HIP 58181",
      "raDeg": 178.993365,
      "decDeg": 56.598563,
      "pmRaMasYr": 7.7,
      "pmDecMasYr": -1.22,
      "parallaxMas": 10.34,
      "mag": 5.83,
      "colorIndex": 1.101,
      "tier": "T1"
    },
    {
      "id": "hip-33377",
      "sourceId": "HIP 33377",
      "raDeg": 104.133585,
      "decDeg": 46.273986,
      "pmRaMasYr": -3.59,
      "pmDecMasYr": 4.98,
      "parallaxMas": 3.95,
      "mag": 5.85,
      "colorIndex": -0.079,
      "tier": "T1"
    },
    {
      "id": "hip-31039",
      "sourceId": "HIP 31039",
      "raDeg": 97.696422,
      "decDeg": 58.163457,
      "pmRaMasYr": -30.02,
      "pmDecMasYr": -338.85,
      "parallaxMas": 17.56,
      "mag": 5.86,
      "colorIndex": 0.934,
      "tier": "T1"
    },
    {
      "id": "hip-48893",
      "sourceId": "HIP 48893",
      "raDeg": 149.595458,
      "decDeg": 72.879598,
      "pmRaMasYr": -69.92,
      "pmDecMasYr": -36.52,
      "parallaxMas": 8.81,
      "mag": 5.86,
      "colorIndex": 1.155,
      "tier": "T1"
    },
    {
      "id": "hip-31665",
      "sourceId": "HIP 31665",
      "raDeg": 99.409995,
      "decDeg": 56.857507,
      "pmRaMasYr": -9.26,
      "pmDecMasYr": 9.79,
      "parallaxMas": 10.12,
      "mag": 5.87,
      "colorIndex": 0.006,
      "tier": "T1"
    },
    {
      "id": "hip-30972",
      "sourceId": "HIP 30972",
      "raDeg": 97.512417,
      "decDeg": 46.685536,
      "pmRaMasYr": -6.64,
      "pmDecMasYr": 7.5,
      "parallaxMas": 6.15,
      "mag": 5.88,
      "colorIndex": 1.448,
      "tier": "T1"
    },
    {
      "id": "hip-31946",
      "sourceId": "HIP 31946",
      "raDeg": 100.13435,
      "decDeg": 71.74876,
      "pmRaMasYr": 4.23,
      "pmDecMasYr": 10.7,
      "parallaxMas": 4.92,
      "mag": 5.88,
      "colorIndex": 1.223,
      "tier": "T1"
    },
    {
      "id": "hip-33415",
      "sourceId": "HIP 33415",
      "raDeg": 104.233871,
      "decDeg": 46.705538,
      "pmRaMasYr": -92.66,
      "pmDecMasYr": -76.25,
      "parallaxMas": 9.76,
      "mag": 5.88,
      "colorIndex": 1.093,
      "tier": "T1"
    },
    {
      "id": "hip-40305",
      "sourceId": "HIP 40305",
      "raDeg": 123.45916,
      "decDeg": 56.452318,
      "pmRaMasYr": -21.44,
      "pmDecMasYr": -29.59,
      "parallaxMas": 6.59,
      "mag": 5.88,
      "colorIndex": 1.016,
      "tier": "T1"
    },
    {
      "id": "hip-50685",
      "sourceId": "HIP 50685",
      "raDeg": 155.264284,
      "decDeg": 68.747734,
      "pmRaMasYr": -54.63,
      "pmDecMasYr": -34.17,
      "parallaxMas": 7.95,
      "mag": 5.88,
      "colorIndex": 0.241,
      "tier": "T1"
    },
    {
      "id": "hip-55086",
      "sourceId": "HIP 55086",
      "raDeg": 169.174692,
      "decDeg": 49.476277,
      "pmRaMasYr": -85.18,
      "pmDecMasYr": -11.02,
      "parallaxMas": 7.74,
      "mag": 5.88,
      "colorIndex": 1.102,
      "tier": "T1"
    },
    {
      "id": "hip-40875",
      "sourceId": "HIP 40875",
      "raDeg": 125.108322,
      "decDeg": 57.743245,
      "pmRaMasYr": 57.08,
      "pmDecMasYr": 13.92,
      "parallaxMas": 31.57,
      "mag": 5.89,
      "colorIndex": 0.421,
      "tier": "T1"
    },
    {
      "id": "hip-41676",
      "sourceId": "HIP 41676",
      "raDeg": 127.442892,
      "decDeg": 67.297415,
      "pmRaMasYr": -65.13,
      "pmDecMasYr": 10.67,
      "parallaxMas": 10.12,
      "mag": 5.89,
      "colorIndex": 0.972,
      "tier": "T1"
    },
    {
      "id": "hip-39995",
      "sourceId": "HIP 39995",
      "raDeg": 122.515832,
      "decDeg": 58.248423,
      "pmRaMasYr": -19.45,
      "pmDecMasYr": -74.21,
      "parallaxMas": 5.82,
      "mag": 5.91,
      "colorIndex": 1.365,
      "tier": "T1"
    },
    {
      "id": "hip-42452",
      "sourceId": "HIP 42452",
      "raDeg": 129.823546,
      "decDeg": 52.711699,
      "pmRaMasYr": -29.26,
      "pmDecMasYr": -31.38,
      "parallaxMas": 8.21,
      "mag": 5.91,
      "colorIndex": 1.167,
      "tier": "T1"
    },
    {
      "id": "hip-53257",
      "sourceId": "HIP 53257",
      "raDeg": 163.38075,
      "decDeg": 69.854045,
      "pmRaMasYr": -397.51,
      "pmDecMasYr": -67.48,
      "parallaxMas": 23.02,
      "mag": 5.91,
      "colorIndex": 1.01,
      "tier": "T1"
    },
    {
      "id": "hip-35304",
      "sourceId": "HIP 35304",
      "raDeg": 109.390501,
      "decDeg": 52.131115,
      "pmRaMasYr": -0.63,
      "pmDecMasYr": -17.8,
      "parallaxMas": 5.35,
      "mag": 5.93,
      "colorIndex": 1.259,
      "tier": "T1"
    },
    {
      "id": "hip-37046",
      "sourceId": "HIP 37046",
      "raDeg": 114.196028,
      "decDeg": 55.755155,
      "pmRaMasYr": -10.87,
      "pmDecMasYr": -39.0,
      "parallaxMas": 11.63,
      "mag": 5.93,
      "colorIndex": 1.123,
      "tier": "T1"
    },
    {
      "id": "hip-37140",
      "sourceId": "HIP 37140",
      "raDeg": 114.474495,
      "decDeg": 48.773911,
      "pmRaMasYr": -32.62,
      "pmDecMasYr": -28.48,
      "parallaxMas": 12.44,
      "mag": 5.93,
      "colorIndex": 0.221,
      "tier": "T1"
    },
    {
      "id": "hip-37949",
      "sourceId": "HIP 37949",
      "raDeg": 116.66683,
      "decDeg": 65.455631,
      "pmRaMasYr": 28.15,
      "pmDecMasYr": 18.39,
      "parallaxMas": 9.82,
      "mag": 5.93,
      "colorIndex": 1.183,
      "tier": "T1"
    },
    {
      "id": "hip-45461",
      "sourceId": "HIP 45461",
      "raDeg": 138.969791,
      "decDeg": 72.946462,
      "pmRaMasYr": -85.32,
      "pmDecMasYr": -56.0,
      "parallaxMas": 11.21,
      "mag": 5.93,
      "colorIndex": 0.179,
      "tier": "T1"
    },
    {
      "id": "hip-31676",
      "sourceId": "HIP 31676",
      "raDeg": 99.423501,
      "decDeg": 61.4819,
      "pmRaMasYr": -208.21,
      "pmDecMasYr": -274.56,
      "parallaxMas": 18.82,
      "mag": 5.94,
      "colorIndex": 0.899,
      "tier": "T1"
    },
    {
      "id": "hip-52577",
      "sourceId": "HIP 52577",
      "raDeg": 161.266761,
      "decDeg": 67.411382,
      "pmRaMasYr": 4.38,
      "pmDecMasYr": 0.74,
      "parallaxMas": 2.88,
      "mag": 5.95,
      "colorIndex": 2.382,
      "tier": "T1"
    },
    {
      "id": "hip-43553",
      "sourceId": "HIP 43553",
      "raDeg": 133.049073,
      "decDeg": 45.3129,
      "pmRaMasYr": -11.02,
      "pmDecMasYr": -33.32,
      "parallaxMas": 6.06,
      "mag": 5.96,
      "colorIndex": 1.233,
      "tier": "T1"
    },
    {
      "id": "hip-45590",
      "sourceId": "HIP 45590",
      "raDeg": 139.379857,
      "decDeg": 46.817199,
      "pmRaMasYr": 14.11,
      "pmDecMasYr": 11.91,
      "parallaxMas": 8.89,
      "mag": 5.96,
      "colorIndex": 0.063,
      "tier": "T1"
    },
    {
      "id": "hip-47401",
      "sourceId": "HIP 47401",
      "raDeg": 144.866319,
      "decDeg": 67.272324,
      "pmRaMasYr": -27.75,
      "pmDecMasYr": -38.67,
      "parallaxMas": 6.0,
      "mag": 5.96,
      "colorIndex": 1.528,
      "tier": "T1"
    },
    {
      "id": "hip-48802",
      "sourceId": "HIP 48802",
      "raDeg": 149.30655,
      "decDeg": 57.418351,
      "pmRaMasYr": 35.74,
      "pmDecMasYr": -63.78,
      "parallaxMas": 6.99,
      "mag": 5.97,
      "colorIndex": 0.895,
      "tier": "T1"
    },
    {
      "id": "hip-28562",
      "sourceId": "HIP 28562",
      "raDeg": 90.429386,
      "decDeg": 48.959469,
      "pmRaMasYr": 7.1,
      "pmDecMasYr": -9.89,
      "parallaxMas": 4.75,
      "mag": 5.98,
      "colorIndex": 1.437,
      "tier": "T1"
    },
    {
      "id": "hip-40889",
      "sourceId": "HIP 40889",
      "raDeg": 125.167982,
      "decDeg": 72.407293,
      "pmRaMasYr": 2.52,
      "pmDecMasYr": -24.97,
      "parallaxMas": 3.44,
      "mag": 6.0,
      "colorIndex": 1.537,
      "tier": "T1"
    },
    {
      "id": "hip-50546",
      "sourceId": "HIP 50546",
      "raDeg": 154.862006,
      "decDeg": 48.397031,
      "pmRaMasYr": -105.97,
      "pmDecMasYr": -110.66,
      "parallaxMas": 23.08,
      "mag": 6.0,
      "colorIndex": 1.022,
      "tier": "T1"
    },
    {
      "id": "hip-50635",
      "sourceId": "HIP 50635",
      "raDeg": 155.129934,
      "decDeg": 54.216854,
      "pmRaMasYr": -34.89,
      "pmDecMasYr": -6.03,
      "parallaxMas": 7.13,
      "mag": 6.01,
      "colorIndex": 1.128,
      "tier": "T1"
    },
    {
      "id": "hip-39261",
      "sourceId": "HIP 39261",
      "raDeg": 120.427057,
      "decDeg": 60.324408,
      "pmRaMasYr": -33.56,
      "pmDecMasYr": -22.24,
      "parallaxMas": 10.16,
      "mag": 6.02,
      "colorIndex": 0.158,
      "tier": "T1"
    },
    {
      "id": "hip-55564",
      "sourceId": "HIP 55564",
      "raDeg": 170.713544,
      "decDeg": 64.330427,
      "pmRaMasYr": -4.48,
      "pmDecMasYr": 35.35,
      "parallaxMas": 11.58,
      "mag": 6.02,
      "colorIndex": 0.085,
      "tier": "T1"
    },
    {
      "id": "hip-30794",
      "sourceId": "HIP 30794",
      "raDeg": 97.060358,
      "decDeg": 70.535291,
      "pmRaMasYr": -0.76,
      "pmDecMasYr": 11.81,
      "parallaxMas": 5.89,
      "mag": 6.03,
      "colorIndex": 0.103,
      "tier": "T1"
    },
    {
      "id": "hip-33444",
      "sourceId": "HIP 33444",
      "raDeg": 104.304685,
      "decDeg": 57.563249,
      "pmRaMasYr": 13.15,
      "pmDecMasYr": 15.61,
      "parallaxMas": 4.87,
      "mag": 6.03,
      "colorIndex": 1.495,
      "tier": "T1"
    },
    {
      "id": "hip-38325",
      "sourceId": "HIP 38325",
      "raDeg": 117.773961,
      "decDeg": 54.129111,
      "pmRaMasYr": -40.3,
      "pmDecMasYr": 53.28,
      "parallaxMas": 33.32,
      "mag": 6.03,
      "colorIndex": 0.496,
      "tier": "T1"
    },
    {
      "id": "hip-28637",
      "sourceId": "HIP 28637",
      "raDeg": 90.702456,
      "decDeg": 49.905785,
      "pmRaMasYr": 14.37,
      "pmDecMasYr": -43.75,
      "parallaxMas": 7.95,
      "mag": 6.04,
      "colorIndex": -0.033,
      "tier": "T1"
    },
    {
      "id": "hip-30272",
      "sourceId": "HIP 30272",
      "raDeg": 95.514826,
      "decDeg": 59.372098,
      "pmRaMasYr": -5.55,
      "pmDecMasYr": 0.6,
      "parallaxMas": 7.73,
      "mag": 6.05,
      "colorIndex": 0.153,
      "tier": "T1"
    },
    {
      "id": "hip-29569",
      "sourceId": "HIP 29569",
      "raDeg": 93.438931,
      "decDeg": 51.172624,
      "pmRaMasYr": -2.07,
      "pmDecMasYr": -63.63,
      "parallaxMas": 8.08,
      "mag": 6.07,
      "colorIndex": 1.051,
      "tier": "T1"
    },
    {
      "id": "hip-51448",
      "sourceId": "HIP 51448",
      "raDeg": 157.611057,
      "decDeg": 64.257813,
      "pmRaMasYr": -50.85,
      "pmDecMasYr": -50.74,
      "parallaxMas": 11.27,
      "mag": 6.07,
      "colorIndex": 0.178,
      "tier": "T1"
    },
    {
      "id": "hip-54540",
      "sourceId": "HIP 54540",
      "raDeg": 167.416324,
      "decDeg": 67.210275,
      "pmRaMasYr": -87.45,
      "pmDecMasYr": -27.39,
      "parallaxMas": 9.18,
      "mag": 6.07,
      "colorIndex": 0.225,
      "tier": "T1"
    },
    {
      "id": "hip-37406",
      "sourceId": "HIP 37406",
      "raDeg": 115.206491,
      "decDeg": 57.082875,
      "pmRaMasYr": -24.11,
      "pmDecMasYr": -4.35,
      "parallaxMas": 4.67,
      "mag": 6.09,
      "colorIndex": 1.44,
      "tier": "T1"
    },
    {
      "id": "hip-39340",
      "sourceId": "HIP 39340",
      "raDeg": 120.628429,
      "decDeg": 63.09034,
      "pmRaMasYr": -12.01,
      "pmDecMasYr": -13.79,
      "parallaxMas": 6.24,
      "mag": 6.09,
      "colorIndex": 0.58,
      "tier": "T1"
    },
    {
      "id": "hip-48017",
      "sourceId": "HIP 48017",
      "raDeg": 146.825569,
      "decDeg": 79.13673,
      "pmRaMasYr": -29.88,
      "pmDecMasYr": -20.44,
      "parallaxMas": 7.83,
      "mag": 6.09,
      "colorIndex": 0.303,
      "tier": "T1"
    },
    {
      "id": "hip-56789",
      "sourceId": "HIP 56789",
      "raDeg": 174.639763,
      "decDeg": 46.834276,
      "pmRaMasYr": -35.43,
      "pmDecMasYr": -27.36,
      "parallaxMas": 9.29,
      "mag": 6.09,
      "colorIndex": 0.401,
      "tier": "T1"
    },
    {
      "id": "hip-56253",
      "sourceId": "HIP 56253",
      "raDeg": 172.962829,
      "decDeg": 81.127174,
      "pmRaMasYr": -144.22,
      "pmDecMasYr": 34.19,
      "parallaxMas": 16.72,
      "mag": 6.12,
      "colorIndex": 0.264,
      "tier": "T1"
    },
    {
      "id": "hip-45836",
      "sourceId": "HIP 45836",
      "raDeg": 140.182476,
      "decDeg": 51.265713,
      "pmRaMasYr": -34.76,
      "pmDecMasYr": 145.35,
      "parallaxMas": 34.48,
      "mag": 6.14,
      "colorIndex": 0.436,
      "tier": "T1"
    },
    {
      "id": "hip-56731",
      "sourceId": "HIP 56731",
      "raDeg": 174.471033,
      "decDeg": 50.618275,
      "pmRaMasYr": -47.33,
      "pmDecMasYr": -26.48,
      "parallaxMas": 7.07,
      "mag": 6.14,
      "colorIndex": 1.068,
      "tier": "T1"
    },
    {
      "id": "hip-42484",
      "sourceId": "HIP 42484",
      "raDeg": 129.927654,
      "decDeg": 73.629919,
      "pmRaMasYr": -13.45,
      "pmDecMasYr": -99.01,
      "parallaxMas": 9.18,
      "mag": 6.16,
      "colorIndex": 1.017,
      "tier": "T1"
    },
    {
      "id": "hip-28532",
      "sourceId": "HIP 28532",
      "raDeg": 90.334047,
      "decDeg": 85.182118,
      "pmRaMasYr": 14.66,
      "pmDecMasYr": -1.89,
      "parallaxMas": 2.44,
      "mag": 6.17,
      "colorIndex": 1.564,
      "tier": "T1"
    },
    {
      "id": "hip-34217",
      "sourceId": "HIP 34217",
      "raDeg": 106.415945,
      "decDeg": 52.758685,
      "pmRaMasYr": -34.28,
      "pmDecMasYr": -52.38,
      "parallaxMas": 9.4,
      "mag": 6.17,
      "colorIndex": 0.102,
      "tier": "T1"
    },
    {
      "id": "hip-47791",
      "sourceId": "HIP 47791",
      "raDeg": 146.152604,
      "decDeg": 64.984066,
      "pmRaMasYr": -54.96,
      "pmDecMasYr": 19.22,
      "parallaxMas": 9.29,
      "mag": 6.18,
      "colorIndex": 0.419,
      "tier": "T1"
    },
    {
      "id": "hip-50222",
      "sourceId": "HIP 50222",
      "raDeg": 153.781877,
      "decDeg": 59.985527,
      "pmRaMasYr": 14.22,
      "pmDecMasYr": 5.14,
      "parallaxMas": 1.87,
      "mag": 6.18,
      "colorIndex": 1.621,
      "tier": "T1"
    },
    {
      "id": "hip-53761",
      "sourceId": "HIP 53761",
      "raDeg": 164.987578,
      "decDeg": 77.770225,
      "pmRaMasYr": -70.28,
      "pmDecMasYr": -20.8,
      "parallaxMas": 5.89,
      "mag": 6.18,
      "colorIndex": 0.966,
      "tier": "T1"
    },
    {
      "id": "hip-43266",
      "sourceId": "HIP 43266",
      "raDeg": 132.205333,
      "decDeg": 66.708168,
      "pmRaMasYr": -19.93,
      "pmDecMasYr": -35.26,
      "parallaxMas": 6.34,
      "mag": 6.2,
      "colorIndex": -0.106,
      "tier": "T1"
    },
    {
      "id": "hip-46410",
      "sourceId": "HIP 46410",
      "raDeg": 141.965109,
      "decDeg": 75.0983,
      "pmRaMasYr": -15.39,
      "pmDecMasYr": 16.95,
      "parallaxMas": 6.88,
      "mag": 6.2,
      "colorIndex": 0.115,
      "tier": "T1"
    },
    {
      "id": "hip-55412",
      "sourceId": "HIP 55412",
      "raDeg": 170.223786,
      "decDeg": 67.100856,
      "pmRaMasYr": 43.78,
      "pmDecMasYr": -50.16,
      "parallaxMas": 7.42,
      "mag": 6.2,
      "colorIndex": 1.018,
      "tier": "T1"
    },
    {
      "id": "hip-42777",
      "sourceId": "HIP 42777",
      "raDeg": 130.750809,
      "decDeg": 46.900995,
      "pmRaMasYr": -47.9,
      "pmDecMasYr": -61.63,
      "parallaxMas": 7.92,
      "mag": 6.21,
      "colorIndex": 0.981,
      "tier": "T1"
    },
    {
      "id": "hip-53706",
      "sourceId": "HIP 53706",
      "raDeg": 164.824549,
      "decDeg": 51.882368,
      "pmRaMasYr": -18.02,
      "pmDecMasYr": -3.85,
      "parallaxMas": 4.79,
      "mag": 6.22,
      "colorIndex": 1.352,
      "tier": "T1"
    },
    {
      "id": "hip-58259",
      "sourceId": "HIP 58259",
      "raDeg": 179.221971,
      "decDeg": 61.549319,
      "pmRaMasYr": -30.51,
      "pmDecMasYr": -43.4,
      "parallaxMas": 5.33,
      "mag": 6.22,
      "colorIndex": 0.955,
      "tier": "T1"
    },
    {
      "id": "hip-41894",
      "sourceId": "HIP 41894",
      "raDeg": 128.139329,
      "decDeg": 53.115028,
      "pmRaMasYr": 9.87,
      "pmDecMasYr": -74.13,
      "parallaxMas": 16.65,
      "mag": 6.23,
      "colorIndex": 1.008,
      "tier": "T1"
    },
    {
      "id": "hip-46247",
      "sourceId": "HIP 46247",
      "raDeg": 141.434114,
      "decDeg": 63.941026,
      "pmRaMasYr": -12.55,
      "pmDecMasYr": -35.58,
      "parallaxMas": 4.03,
      "mag": 6.24,
      "colorIndex": 1.465,
      "tier": "T1"
    },
    {
      "id": "hip-38623",
      "sourceId": "HIP 38623",
      "raDeg": 118.621992,
      "decDeg": 47.385973,
      "pmRaMasYr": -16.08,
      "pmDecMasYr": 3.55,
      "parallaxMas": 5.3,
      "mag": 6.25,
      "colorIndex": 1.133,
      "tier": "T1"
    },
    {
      "id": "hip-47884",
      "sourceId": "HIP 47884",
      "raDeg": 146.378999,
      "decDeg": 78.134713,
      "pmRaMasYr": 8.96,
      "pmDecMasYr": -1.58,
      "parallaxMas": 3.22,
      "mag": 6.25,
      "colorIndex": 1.353,
      "tier": "T1"
    },
    {
      "id": "hip-31703",
      "sourceId": "HIP 31703",
      "raDeg": 99.480177,
      "decDeg": 73.695629,
      "pmRaMasYr": -169.55,
      "pmDecMasYr": 2.65,
      "parallaxMas": 28.12,
      "mag": 6.26,
      "colorIndex": 0.396,
      "tier": "T1"
    },
    {
      "id": "hip-40677",
      "sourceId": "HIP 40677",
      "raDeg": 124.565873,
      "decDeg": 54.143768,
      "pmRaMasYr": -21.3,
      "pmDecMasYr": -29.62,
      "parallaxMas": 3.06,
      "mag": 6.26,
      "colorIndex": 1.558,
      "tier": "T1"
    },
    {
      "id": "hip-48266",
      "sourceId": "HIP 48266",
      "raDeg": 147.598612,
      "decDeg": 65.593296,
      "pmRaMasYr": -58.5,
      "pmDecMasYr": -28.38,
      "parallaxMas": 10.65,
      "mag": 6.27,
      "colorIndex": 0.29,
      "tier": "T1"
    },
    {
      "id": "hip-28831",
      "sourceId": "HIP 28831",
      "raDeg": 91.288835,
      "decDeg": 75.585943,
      "pmRaMasYr": 10.97,
      "pmDecMasYr": -9.99,
      "parallaxMas": 4.53,
      "mag": 6.28,
      "colorIndex": 1.512,
      "tier": "T1"
    },
    {
      "id": "hip-29404",
      "sourceId": "HIP 29404",
      "raDeg": 92.941292,
      "decDeg": 52.647364,
      "pmRaMasYr": 4.06,
      "pmDecMasYr": -73.13,
      "parallaxMas": 9.97,
      "mag": 6.28,
      "colorIndex": 0.141,
      "tier": "T1"
    },
    {
      "id": "hip-32261",
      "sourceId": "HIP 32261",
      "raDeg": 101.04782,
      "decDeg": 53.296427,
      "pmRaMasYr": 34.68,
      "pmDecMasYr": -200.98,
      "parallaxMas": 13.27,
      "mag": 6.28,
      "colorIndex": 1.089,
      "tier": "T1"
    },
    {
      "id": "hip-41208",
      "sourceId": "HIP 41208",
      "raDeg": 126.137945,
      "decDeg": 82.430822,
      "pmRaMasYr": -19.31,
      "pmDecMasYr": -25.9,
      "parallaxMas": 4.8,
      "mag": 6.28,
      "colorIndex": 0.035,
      "tier": "T1"
    },
    {
      "id": "hip-57045",
      "sourceId": "HIP 57045",
      "raDeg": 175.431322,
      "decDeg": 55.171993,
      "pmRaMasYr": -19.67,
      "pmDecMasYr": 7.28,
      "parallaxMas": 3.24,
      "mag": 6.28,
      "colorIndex": 1.491,
      "tier": "T1"
    },
    {
      "id": "hip-48638",
      "sourceId": "HIP 48638",
      "raDeg": 148.76395,
      "decDeg": 61.116131,
      "pmRaMasYr": 7.79,
      "pmDecMasYr": -3.24,
      "parallaxMas": 8.39,
      "mag": 6.29,
      "colorIndex": 1.036,
      "tier": "T1"
    },
    {
      "id": "hip-56083",
      "sourceId": "HIP 56083",
      "raDeg": 172.431914,
      "decDeg": 56.737655,
      "pmRaMasYr": -89.53,
      "pmDecMasYr": -33.79,
      "parallaxMas": 14.73,
      "mag": 6.29,
      "colorIndex": 0.157,
      "tier": "T1"
    },
    {
      "id": "hip-56809",
      "sourceId": "HIP 56809",
      "raDeg": 174.689132,
      "decDeg": 45.10838,
      "pmRaMasYr": -593.87,
      "pmDecMasYr": 14.8,
      "parallaxMas": 42.94,
      "mag": 6.29,
      "colorIndex": 0.566,
      "tier": "T1"
    },
    {
      "id": "hip-36019",
      "sourceId": "HIP 36019",
      "raDeg": 111.341544,
      "decDeg": 81.257533,
      "pmRaMasYr": -2.3,
      "pmDecMasYr": -31.84,
      "parallaxMas": 3.92,
      "mag": 6.3,
      "colorIndex": -0.031,
      "tier": "T1"
    },
    {
      "id": "hip-45421",
      "sourceId": "HIP 45421",
      "raDeg": 138.83849,
      "decDeg": 84.180988,
      "pmRaMasYr": 32.78,
      "pmDecMasYr": 10.3,
      "parallaxMas": 11.1,
      "mag": 6.3,
      "colorIndex": 0.339,
      "tier": "T1"
    },
    {
      "id": "hip-46168",
      "sourceId": "HIP 46168",
      "raDeg": 141.23184,
      "decDeg": 51.573915,
      "pmRaMasYr": 42.41,
      "pmDecMasYr": -7.86,
      "parallaxMas": 7.55,
      "mag": 6.3,
      "colorIndex": 0.774,
      "tier": "T1"
    },
    {
      "id": "hip-56135",
      "sourceId": "HIP 56135",
      "raDeg": 172.603457,
      "decDeg": 46.657466,
      "pmRaMasYr": -5.36,
      "pmDecMasYr": 27.66,
      "parallaxMas": 3.31,
      "mag": 6.3,
      "colorIndex": 1.265,
      "tier": "T1"
    },
    {
      "id": "hip-33271",
      "sourceId": "HIP 33271",
      "raDeg": 103.813389,
      "decDeg": 45.826588,
      "pmRaMasYr": -31.15,
      "pmDecMasYr": -73.84,
      "parallaxMas": 8.52,
      "mag": 6.31,
      "colorIndex": 0.945,
      "tier": "T1"
    },
    {
      "id": "hip-41927",
      "sourceId": "HIP 41927",
      "raDeg": 128.221966,
      "decDeg": 69.319963,
      "pmRaMasYr": 22.92,
      "pmDecMasYr": -25.21,
      "parallaxMas": 5.27,
      "mag": 6.31,
      "colorIndex": 1.36,
      "tier": "T1"
    },
    {
      "id": "hip-42249",
      "sourceId": "HIP 42249",
      "raDeg": 129.203243,
      "decDeg": 74.72372,
      "pmRaMasYr": -16.05,
      "pmDecMasYr": -17.74,
      "parallaxMas": 11.92,
      "mag": 6.31,
      "colorIndex": 0.308,
      "tier": "T1"
    },
    {
      "id": "hip-49408",
      "sourceId": "HIP 49408",
      "raDeg": 151.293314,
      "decDeg": 52.371314,
      "pmRaMasYr": -14.01,
      "pmDecMasYr": -4.92,
      "parallaxMas": 9.88,
      "mag": 6.31,
      "colorIndex": 0.135,
      "tier": "T1"
    },
    {
      "id": "hip-49688",
      "sourceId": "HIP 49688",
      "raDeg": 152.143323,
      "decDeg": 83.918357,
      "pmRaMasYr": -1.21,
      "pmDecMasYr": 6.27,
      "parallaxMas": 3.69,
      "mag": 6.31,
      "colorIndex": 1.549,
      "tier": "T1"
    },
    {
      "id": "hip-28829",
      "sourceId": "HIP 28829",
      "raDeg": 91.284273,
      "decDeg": 59.393331,
      "pmRaMasYr": 2.69,
      "pmDecMasYr": -49.56,
      "parallaxMas": 6.92,
      "mag": 6.32,
      "colorIndex": 1.116,
      "tier": "T1"
    },
    {
      "id": "hip-41484",
      "sourceId": "HIP 41484",
      "raDeg": 126.903339,
      "decDeg": 45.653841,
      "pmRaMasYr": -18.98,
      "pmDecMasYr": -351.48,
      "parallaxMas": 45.89,
      "mag": 6.32,
      "colorIndex": 0.624,
      "tier": "T1"
    },
    {
      "id": "hip-51401",
      "sourceId": "HIP 51401",
      "raDeg": 157.476787,
      "decDeg": 65.626304,
      "pmRaMasYr": 5.21,
      "pmDecMasYr": -29.16,
      "parallaxMas": 10.41,
      "mag": 6.32,
      "colorIndex": 1.141,
      "tier": "T1"
    },
    {
      "id": "hip-29949",
      "sourceId": "HIP 29949",
      "raDeg": 94.570229,
      "decDeg": 46.36076,
      "pmRaMasYr": 12.56,
      "pmDecMasYr": -130.38,
      "parallaxMas": 9.43,
      "mag": 6.33,
      "colorIndex": 1.113,
      "tier": "T1"
    },
    {
      "id": "hip-42415",
      "sourceId": "HIP 42415",
      "raDeg": 129.749654,
      "decDeg": 52.925148,
      "pmRaMasYr": -28.67,
      "pmDecMasYr": -28.44,
      "parallaxMas": 5.61,
      "mag": 6.34,
      "colorIndex": 1.319,
      "tier": "T1"
    },
    {
      "id": "hip-48861",
      "sourceId": "HIP 48861",
      "raDeg": 149.486836,
      "decDeg": 45.414381,
      "pmRaMasYr": 6.43,
      "pmDecMasYr": -34.11,
      "parallaxMas": 7.8,
      "mag": 6.34,
      "colorIndex": 1.096,
      "tier": "T1"
    },
    {
      "id": "hip-52685",
      "sourceId": "HIP 52685",
      "raDeg": 161.593908,
      "decDeg": 57.366054,
      "pmRaMasYr": -53.18,
      "pmDecMasYr": -57.57,
      "parallaxMas": 4.31,
      "mag": 6.34,
      "colorIndex": 1.568,
      "tier": "T1"
    },
    {
      "id": "hip-43624",
      "sourceId": "HIP 43624",
      "raDeg": 133.274706,
      "decDeg": 59.056143,
      "pmRaMasYr": 15.5,
      "pmDecMasYr": -1.18,
      "parallaxMas": 16.19,
      "mag": 6.35,
      "colorIndex": 0.414,
      "tier": "T1"
    },
    {
      "id": "hip-56944",
      "sourceId": "HIP 56944",
      "raDeg": 175.114333,
      "decDeg": 57.970374,
      "pmRaMasYr": -9.39,
      "pmDecMasYr": 12.68,
      "parallaxMas": 6.2,
      "mag": 6.35,
      "colorIndex": -0.092,
      "tier": "T1"
    },
    {
      "id": "hip-34956",
      "sourceId": "HIP 34956",
      "raDeg": 108.491633,
      "decDeg": 71.816539,
      "pmRaMasYr": 23.39,
      "pmDecMasYr": 18.54,
      "parallaxMas": 8.24,
      "mag": 6.36,
      "colorIndex": 1.119,
      "tier": "T1"
    },
    {
      "id": "hip-35735",
      "sourceId": "HIP 35735",
      "raDeg": 110.57161,
      "decDeg": 59.901959,
      "pmRaMasYr": -1.72,
      "pmDecMasYr": 15.4,
      "parallaxMas": 14.23,
      "mag": 6.36,
      "colorIndex": 0.282,
      "tier": "T1"
    },
    {
      "id": "hip-38449",
      "sourceId": "HIP 38449",
      "raDeg": 118.151885,
      "decDeg": 55.209546,
      "pmRaMasYr": -21.76,
      "pmDecMasYr": -42.2,
      "parallaxMas": 7.41,
      "mag": 6.36,
      "colorIndex": -0.003,
      "tier": "T1"
    },
    {
      "id": "hip-47633",
      "sourceId": "HIP 47633",
      "raDeg": 145.679667,
      "decDeg": 48.431058,
      "pmRaMasYr": -30.54,
      "pmDecMasYr": -23.75,
      "parallaxMas": 7.49,
      "mag": 6.36,
      "colorIndex": 0.01,
      "tier": "T1"
    },
    {
      "id": "hip-34168",
      "sourceId": "HIP 34168",
      "raDeg": 106.28745,
      "decDeg": 47.775043,
      "pmRaMasYr": 0.28,
      "pmDecMasYr": 0.09,
      "parallaxMas": 2.36,
      "mag": 6.37,
      "colorIndex": -0.048,
      "tier": "T1"
    },
    {
      "id": "hip-45097",
      "sourceId": "HIP 45097",
      "raDeg": 137.803032,
      "decDeg": 80.828946,
      "pmRaMasYr": -20.66,
      "pmDecMasYr": -15.02,
      "parallaxMas": 12.95,
      "mag": 6.37,
      "colorIndex": 0.385,
      "tier": "T1"
    },
    {
      "id": "hip-51290",
      "sourceId": "HIP 51290",
      "raDeg": 157.152241,
      "decDeg": 45.212263,
      "pmRaMasYr": -21.8,
      "pmDecMasYr": -21.03,
      "parallaxMas": 4.27,
      "mag": 6.37,
      "colorIndex": 1.33,
      "tier": "T1"
    },
    {
      "id": "hip-53860",
      "sourceId": "HIP 53860",
      "raDeg": 165.273858,
      "decDeg": 63.421235,
      "pmRaMasYr": -51.01,
      "pmDecMasYr": -51.42,
      "parallaxMas": 11.47,
      "mag": 6.38,
      "colorIndex": 0.169,
      "tier": "T1"
    },
    {
      "id": "hip-28765",
      "sourceId": "HIP 28765",
      "raDeg": 91.121274,
      "decDeg": 51.573499,
      "pmRaMasYr": 2.3,
      "pmDecMasYr": -42.82,
      "parallaxMas": 8.28,
      "mag": 6.39,
      "colorIndex": 0.196,
      "tier": "T1"
    },
    {
      "id": "hip-47260",
      "sourceId": "HIP 47260",
      "raDeg": 144.484535,
      "decDeg": 73.080444,
      "pmRaMasYr": -42.41,
      "pmDecMasYr": -20.33,
      "parallaxMas": 14.37,
      "mag": 6.39,
      "colorIndex": 0.352,
      "tier": "T1"
    },
    {
      "id": "hip-34250",
      "sourceId": "HIP 34250",
      "raDeg": 106.505044,
      "decDeg": 59.801857,
      "pmRaMasYr": 22.0,
      "pmDecMasYr": -2.88,
      "parallaxMas": 9.33,
      "mag": 6.4,
      "colorIndex": 1.19,
      "tier": "T1"
    },
    {
      "id": "hip-41011",
      "sourceId": "HIP 41011",
      "raDeg": 125.539591,
      "decDeg": 74.820254,
      "pmRaMasYr": 48.34,
      "pmDecMasYr": 45.3,
      "parallaxMas": 7.0,
      "mag": 6.4,
      "colorIndex": 1.022,
      "tier": "T1"
    },
    {
      "id": "hip-45888",
      "sourceId": "HIP 45888",
      "raDeg": 140.348379,
      "decDeg": 45.37015,
      "pmRaMasYr": -9.17,
      "pmDecMasYr": -20.19,
      "parallaxMas": 4.57,
      "mag": 6.4,
      "colorIndex": 1.305,
      "tier": "T1"
    },
    {
      "id": "hip-52877",
      "sourceId": "HIP 52877",
      "raDeg": 162.207761,
      "decDeg": 65.132474,
      "pmRaMasYr": 5.09,
      "pmDecMasYr": 7.39,
      "parallaxMas": 7.76,
      "mag": 6.4,
      "colorIndex": -0.022,
      "tier": "T1"
    },
    {
      "id": "hip-54721",
      "sourceId": "HIP 54721",
      "raDeg": 168.045398,
      "decDeg": 68.271854,
      "pmRaMasYr": 27.7,
      "pmDecMasYr": 6.57,
      "parallaxMas": 10.87,
      "mag": 6.4,
      "colorIndex": 0.127,
      "tier": "T1"
    },
    {
      "id": "hip-56170",
      "sourceId": "HIP 56170",
      "raDeg": 172.721428,
      "decDeg": 47.929101,
      "pmRaMasYr": -222.13,
      "pmDecMasYr": -75.26,
      "parallaxMas": 9.93,
      "mag": 6.4,
      "colorIndex": 0.879,
      "tier": "T1"
    },
    {
      "id": "hip-47231",
      "sourceId": "HIP 47231",
      "raDeg": 144.406348,
      "decDeg": 60.213761,
      "pmRaMasYr": -11.78,
      "pmDecMasYr": -32.35,
      "parallaxMas": 10.17,
      "mag": 6.41,
      "colorIndex": 0.921,
      "tier": "T1"
    },
    {
      "id": "hip-53798",
      "sourceId": "HIP 53798",
      "raDeg": 165.106595,
      "decDeg": 51.50214,
      "pmRaMasYr": -29.93,
      "pmDecMasYr": -15.96,
      "parallaxMas": 5.74,
      "mag": 6.41,
      "colorIndex": 1.007,
      "tier": "T1"
    },
    {
      "id": "hip-28951",
      "sourceId": "HIP 28951",
      "raDeg": 91.663337,
      "decDeg": 63.453817,
      "pmRaMasYr": -35.53,
      "pmDecMasYr": 8.74,
      "parallaxMas": 7.87,
      "mag": 6.42,
      "colorIndex": 1.011,
      "tier": "T1"
    },
    {
      "id": "hip-36351",
      "sourceId": "HIP 36351",
      "raDeg": 112.219422,
      "decDeg": 46.314777,
      "pmRaMasYr": -41.6,
      "pmDecMasYr": -65.7,
      "parallaxMas": 9.67,
      "mag": 6.42,
      "colorIndex": 1.202,
      "tier": "T1"
    },
    {
      "id": "hip-41060",
      "sourceId": "HIP 41060",
      "raDeg": 125.683578,
      "decDeg": 60.631241,
      "pmRaMasYr": 9.13,
      "pmDecMasYr": -2.12,
      "parallaxMas": 7.34,
      "mag": 6.42,
      "colorIndex": 0.969,
      "tier": "T1"
    },
    {
      "id": "hip-45764",
      "sourceId": "HIP 45764",
      "raDeg": 139.982437,
      "decDeg": 74.016757,
      "pmRaMasYr": -40.56,
      "pmDecMasYr": -63.87,
      "parallaxMas": 8.8,
      "mag": 6.42,
      "colorIndex": 1.05,
      "tier": "T1"
    },
    {
      "id": "hip-50509",
      "sourceId": "HIP 50509",
      "raDeg": 154.744872,
      "decDeg": 46.760855,
      "pmRaMasYr": -49.37,
      "pmDecMasYr": -31.92,
      "parallaxMas": 3.93,
      "mag": 6.42,
      "colorIndex": 1.19,
      "tier": "T1"
    },
    {
      "id": "hip-51248",
      "sourceId": "HIP 51248",
      "raDeg": 157.015879,
      "decDeg": 48.787044,
      "pmRaMasYr": 80.56,
      "pmDecMasYr": -881.76,
      "parallaxMas": 42.45,
      "mag": 6.42,
      "colorIndex": 0.61,
      "tier": "T1"
    },
    {
      "id": "hip-52929",
      "sourceId": "HIP 52929",
      "raDeg": 162.370076,
      "decDeg": 63.810001,
      "pmRaMasYr": -14.4,
      "pmDecMasYr": 11.58,
      "parallaxMas": 3.78,
      "mag": 6.42,
      "colorIndex": 1.287,
      "tier": "T1"
    },
    {
      "id": "hip-40474",
      "sourceId": "HIP 40474",
      "raDeg": 123.960498,
      "decDeg": 60.380583,
      "pmRaMasYr": -16.12,
      "pmDecMasYr": 7.62,
      "parallaxMas": 6.53,
      "mag": 6.43,
      "colorIndex": 0.21,
      "tier": "T1"
    },
    {
      "id": "hip-55485",
      "sourceId": "HIP 55485",
      "raDeg": 170.455631,
      "decDeg": 57.074843,
      "pmRaMasYr": -58.31,
      "pmDecMasYr": 5.81,
      "parallaxMas": 12.79,
      "mag": 6.43,
      "colorIndex": 0.161,
      "tier": "T1"
    },
    {
      "id": "hip-36779",
      "sourceId": "HIP 36779",
      "raDeg": 113.464699,
      "decDeg": 51.314201,
      "pmRaMasYr": -11.48,
      "pmDecMasYr": -22.56,
      "parallaxMas": 3.73,
      "mag": 6.44,
      "colorIndex": 1.348,
      "tier": "T1"
    },
    {
      "id": "hip-44717",
      "sourceId": "HIP 44717",
      "raDeg": 136.679829,
      "decDeg": 59.344555,
      "pmRaMasYr": -15.25,
      "pmDecMasYr": -14.32,
      "parallaxMas": 2.88,
      "mag": 6.44,
      "colorIndex": 0.045,
      "tier": "T1"
    },
    {
      "id": "hip-53157",
      "sourceId": "HIP 53157",
      "raDeg": 163.133809,
      "decDeg": 52.503731,
      "pmRaMasYr": -58.63,
      "pmDecMasYr": -51.87,
      "parallaxMas": 10.35,
      "mag": 6.44,
      "colorIndex": 1.114,
      "tier": "T1"
    },
    {
      "id": "hip-54038",
      "sourceId": "HIP 54038",
      "raDeg": 165.864028,
      "decDeg": 70.030821,
      "pmRaMasYr": 10.72,
      "pmDecMasYr": -33.19,
      "parallaxMas": 4.44,
      "mag": 6.44,
      "colorIndex": 1.28,
      "tier": "T1"
    },
    {
      "id": "hip-31359",
      "sourceId": "HIP 31359",
      "raDeg": 98.636652,
      "decDeg": 55.353029,
      "pmRaMasYr": 2.69,
      "pmDecMasYr": 5.21,
      "parallaxMas": 2.1,
      "mag": 6.45,
      "colorIndex": 1.554,
      "tier": "T1"
    },
    {
      "id": "hip-40559",
      "sourceId": "HIP 40559",
      "raDeg": 124.224841,
      "decDeg": 84.057689,
      "pmRaMasYr": -9.68,
      "pmDecMasYr": -19.14,
      "parallaxMas": 5.74,
      "mag": 6.45,
      "colorIndex": 0.052,
      "tier": "T1"
    },
    {
      "id": "hip-50606",
      "sourceId": "HIP 50606",
      "raDeg": 155.061998,
      "decDeg": 53.77927,
      "pmRaMasYr": -88.11,
      "pmDecMasYr": 49.87,
      "parallaxMas": 32.7,
      "mag": 6.45,
      "colorIndex": 0.58,
      "tier": "T1"
    },
    {
      "id": "hip-47119",
      "sourceId": "HIP 47119",
      "raDeg": 144.028293,
      "decDeg": 74.318876,
      "pmRaMasYr": -15.55,
      "pmDecMasYr": -29.04,
      "parallaxMas": 7.3,
      "mag": 6.46,
      "colorIndex": -0.083,
      "tier": "T1"
    },
    {
      "id": "hip-30357",
      "sourceId": "HIP 30357",
      "raDeg": 95.776541,
      "decDeg": 56.976525,
      "pmRaMasYr": -0.62,
      "pmDecMasYr": -72.68,
      "parallaxMas": 7.12,
      "mag": 6.47,
      "colorIndex": 1.075,
      "tier": "T1"
    },
    {
      "id": "hip-36211",
      "sourceId": "HIP 36211",
      "raDeg": 111.85768,
      "decDeg": 66.331642,
      "pmRaMasYr": -3.27,
      "pmDecMasYr": -28.93,
      "parallaxMas": 3.65,
      "mag": 6.47,
      "colorIndex": -0.064,
      "tier": "T1"
    },
    {
      "id": "hip-42434",
      "sourceId": "HIP 42434",
      "raDeg": 129.792102,
      "decDeg": 59.939243,
      "pmRaMasYr": -27.41,
      "pmDecMasYr": -48.11,
      "parallaxMas": 9.05,
      "mag": 6.47,
      "colorIndex": 0.035,
      "tier": "T1"
    },
    {
      "id": "hip-29348",
      "sourceId": "HIP 29348",
      "raDeg": 92.806809,
      "decDeg": 60.453527,
      "pmRaMasYr": -21.68,
      "pmDecMasYr": -16.27,
      "parallaxMas": 2.57,
      "mag": 6.48,
      "colorIndex": 1.698,
      "tier": "T1"
    },
    {
      "id": "hip-39348",
      "sourceId": "HIP 39348",
      "raDeg": 120.649262,
      "decDeg": 57.273771,
      "pmRaMasYr": -38.28,
      "pmDecMasYr": -59.08,
      "parallaxMas": 9.84,
      "mag": 6.48,
      "colorIndex": 0.649,
      "tier": "T1"
    },
    {
      "id": "hip-40086",
      "sourceId": "HIP 40086",
      "raDeg": 122.825135,
      "decDeg": 54.540466,
      "pmRaMasYr": 47.34,
      "pmDecMasYr": -93.7,
      "parallaxMas": 5.87,
      "mag": 6.48,
      "colorIndex": 0.94,
      "tier": "T1"
    },
    {
      "id": "hip-51883",
      "sourceId": "HIP 51883",
      "raDeg": 159.008419,
      "decDeg": 80.494638,
      "pmRaMasYr": -18.05,
      "pmDecMasYr": -3.7,
      "parallaxMas": 7.62,
      "mag": 6.48,
      "colorIndex": 0.963,
      "tier": "T1"
    },
    {
      "id": "hip-28634",
      "sourceId": "HIP 28634",
      "raDeg": 90.68797,
      "decDeg": 47.809304,
      "pmRaMasYr": 32.23,
      "pmDecMasYr": 92.58,
      "parallaxMas": 35.21,
      "mag": 6.49,
      "colorIndex": 0.567,
      "tier": "T1"
    },
    {
      "id": "hip-34238",
      "sourceId": "HIP 34238",
      "raDeg": 106.465063,
      "decDeg": 70.73194,
      "pmRaMasYr": 31.28,
      "pmDecMasYr": -6.71,
      "parallaxMas": 3.85,
      "mag": 6.49,
      "colorIndex": 1.568,
      "tier": "T1"
    },
    {
      "id": "hip-46879",
      "sourceId": "HIP 46879",
      "raDeg": 143.296924,
      "decDeg": 45.513853,
      "pmRaMasYr": -15.63,
      "pmDecMasYr": -39.14,
      "parallaxMas": 5.58,
      "mag": 6.49,
      "colorIndex": 1.141,
      "tier": "T1"
    },
    {
      "id": "hip-56716",
      "sourceId": "HIP 56716",
      "raDeg": 174.426303,
      "decDeg": 77.595694,
      "pmRaMasYr": 1.81,
      "pmDecMasYr": 2.15,
      "parallaxMas": 1.92,
      "mag": 6.49,
      "colorIndex": 1.61,
      "tier": "T1"
    },
    {
      "id": "hip-56816",
      "sourceId": "HIP 56816",
      "raDeg": 174.70467,
      "decDeg": 64.346963,
      "pmRaMasYr": 12.47,
      "pmDecMasYr": 1.05,
      "parallaxMas": 5.09,
      "mag": 6.49,
      "colorIndex": 0.154,
      "tier": "T1"
    },
    {
      "id": "hip-28656",
      "sourceId": "HIP 28656",
      "raDeg": 90.767942,
      "decDeg": 57.018425,
      "pmRaMasYr": 9.31,
      "pmDecMasYr": -45.55,
      "parallaxMas": 5.77,
      "mag": 6.5,
      "colorIndex": 0.953,
      "tier": "T1"
    },
    {
      "id": "hip-37934",
      "sourceId": "HIP 37934",
      "raDeg": 116.614423,
      "decDeg": 62.830671,
      "pmRaMasYr": -36.98,
      "pmDecMasYr": -61.01,
      "parallaxMas": 12.32,
      "mag": 6.5,
      "colorIndex": 0.262,
      "tier": "T1"
    },
    {
      "id": "hip-38403",
      "sourceId": "HIP 38403",
      "raDeg": 118.016221,
      "decDeg": 45.933098,
      "pmRaMasYr": -32.72,
      "pmDecMasYr": -44.65,
      "parallaxMas": 9.6,
      "mag": 6.5,
      "colorIndex": 0.213,
      "tier": "T1"
    },
    {
      "id": "hip-40878",
      "sourceId": "HIP 40878",
      "raDeg": 125.121497,
      "decDeg": 53.574352,
      "pmRaMasYr": -64.92,
      "pmDecMasYr": -107.12,
      "parallaxMas": 15.94,
      "mag": 6.5,
      "colorIndex": 0.3,
      "tier": "T1"
    },
    {
      "id": "hip-46566",
      "sourceId": "HIP 46566",
      "raDeg": 142.449454,
      "decDeg": 55.745336,
      "pmRaMasYr": -132.2,
      "pmDecMasYr": -42.17,
      "parallaxMas": 22.55,
      "mag": 6.5,
      "colorIndex": 0.394,
      "tier": "T1"
    },
    {
      "id": "hip-47521",
      "sourceId": "HIP 47521",
      "raDeg": 145.319846,
      "decDeg": 55.866575,
      "pmRaMasYr": -30.5,
      "pmDecMasYr": -34.63,
      "parallaxMas": 7.91,
      "mag": 6.5,
      "colorIndex": 1.15,
      "tier": "T1"
    },
    {
      "id": "hip-47664",
      "sourceId": "HIP 47664",
      "raDeg": 145.779156,
      "decDeg": 54.363785,
      "pmRaMasYr": -31.87,
      "pmDecMasYr": -33.61,
      "parallaxMas": 10.9,
      "mag": 6.5,
      "colorIndex": 0.121,
      "tier": "T1"
    }
  ],
  "labelCandidates": [],
  "provenance": {
    "catalog": "hipparcos",
    "sourcePath": "/home/rocco/Astronomy-Hub/data/sky-engine/hipparcos/source/hip_main.dat",
    "generator": "scripts/sky-engine/build_hipparcos_tiles.py",
    "generatedAt": "2026-04-07T01:17:31.778592Z",
    "sourceRecordCount": 8870,
    "tierSet": [
      "T0",
      "T1"
    ]
  }
}