{
  "tileId": "root-sw-se-ne",
  "level": 2,
  "parentTileId": "root-sw-se",
  "childTileIds": [
    "root-sw-se-ne-nw",
    "root-sw-se-ne-ne",
    "root-sw-se-ne-sw",
    "root-sw-se-ne-se"
  ],
  "bounds": {
    "raMinDeg": 135.0,
    "raMaxDeg": 180,
    "decMinDeg": -67.5,
    "decMaxDeg": -45.0
  },
  "magMin": 2.21,
  "magMax": 6.5,
  "starCount": 254,
  "stars": [
    {
      "id": "hip-45556",
      "sourceId": "HIP 45556",
      "raDeg": 139.272618,
      "decDeg": -59.275261,
      "pmRaMasYr": -19.03,
      "pmDecMasYr": 13.11,
      "parallaxMas": 4.71,
      "mag": 2.21,
      "colorIndex": 0.189,
      "tier": "T0"
    },
    {
      "id": "hip-45941",
      "sourceId": "HIP 45941",
      "raDeg": 140.528455,
      "decDeg": -55.010695,
      "pmRaMasYr": -10.72,
      "pmDecMasYr": 11.24,
      "parallaxMas": 6.05,
      "mag": 2.47,
      "colorIndex": -0.141,
      "tier": "T0"
    },
    {
      "id": "hip-52727",
      "sourceId": "HIP 52727",
      "raDeg": 161.692175,
      "decDeg": -49.420125,
      "pmRaMasYr": 62.55,
      "pmDecMasYr": -53.57,
      "parallaxMas": 28.18,
      "mag": 2.69,
      "colorIndex": 0.901,
      "tier": "T1"
    },
    {
      "id": "hip-52419",
      "sourceId": "HIP 52419",
      "raDeg": 160.739278,
      "decDeg": -64.394479,
      "pmRaMasYr": -18.87,
      "pmDecMasYr": 12.06,
      "parallaxMas": 7.43,
      "mag": 2.74,
      "colorIndex": -0.22,
      "tier": "T1"
    },
    {
      "id": "hip-48002",
      "sourceId": "HIP 48002",
      "raDeg": 146.775573,
      "decDeg": -65.072019,
      "pmRaMasYr": -11.55,
      "pmDecMasYr": 4.97,
      "parallaxMas": 2.01,
      "mag": 2.92,
      "colorIndex": 0.273,
      "tier": "T1"
    },
    {
      "id": "hip-56561",
      "sourceId": "HIP 56561",
      "raDeg": 173.945534,
      "decDeg": -63.019825,
      "pmRaMasYr": -33.84,
      "pmDecMasYr": -6.87,
      "parallaxMas": 7.96,
      "mag": 3.11,
      "colorIndex": -0.044,
      "tier": "T1"
    },
    {
      "id": "hip-46701",
      "sourceId": "HIP 46701",
      "raDeg": 142.805641,
      "decDeg": -57.034392,
      "pmRaMasYr": -32.58,
      "pmDecMasYr": 6.08,
      "parallaxMas": 13.72,
      "mag": 3.16,
      "colorIndex": 1.538,
      "tier": "T1"
    },
    {
      "id": "hip-51576",
      "sourceId": "HIP 51576",
      "raDeg": 158.006182,
      "decDeg": -61.68536,
      "pmRaMasYr": -16.59,
      "pmDecMasYr": 11.42,
      "parallaxMas": 6.56,
      "mag": 3.3,
      "colorIndex": -0.089,
      "tier": "T1"
    },
    {
      "id": "hip-50371",
      "sourceId": "HIP 50371",
      "raDeg": 154.270855,
      "decDeg": -61.33232,
      "pmRaMasYr": -24.25,
      "pmDecMasYr": 6.38,
      "parallaxMas": 4.43,
      "mag": 3.39,
      "colorIndex": 1.541,
      "tier": "T1"
    },
    {
      "id": "hip-45080",
      "sourceId": "HIP 45080",
      "raDeg": 137.742105,
      "decDeg": -58.96693,
      "pmRaMasYr": -17.67,
      "pmDecMasYr": 14.14,
      "parallaxMas": 7.79,
      "mag": 3.43,
      "colorIndex": -0.19,
      "tier": "T1"
    },
    {
      "id": "hip-48774",
      "sourceId": "HIP 48774",
      "raDeg": 149.215645,
      "decDeg": -54.567797,
      "pmRaMasYr": -13.13,
      "pmDecMasYr": 2.83,
      "parallaxMas": 1.69,
      "mag": 3.52,
      "colorIndex": -0.067,
      "tier": "T1"
    },
    {
      "id": "hip-57363",
      "sourceId": "HIP 57363",
      "raDeg": 176.402364,
      "decDeg": -66.728843,
      "pmRaMasYr": -100.42,
      "pmDecMasYr": 33.21,
      "parallaxMas": 25.42,
      "mag": 3.63,
      "colorIndex": 0.16,
      "tier": "T1"
    },
    {
      "id": "hip-47854",
      "sourceId": "HIP 47854",
      "raDeg": 146.311781,
      "decDeg": -62.507923,
      "pmRaMasYr": -12.88,
      "pmDecMasYr": 8.28,
      "parallaxMas": 2.16,
      "mag": 3.69,
      "colorIndex": 1.01,
      "tier": "T1"
    },
    {
      "id": "hip-44511",
      "sourceId": "HIP 44511",
      "raDeg": 136.038836,
      "decDeg": -47.097714,
      "pmRaMasYr": -46.82,
      "pmDecMasYr": -9.57,
      "parallaxMas": 10.55,
      "mag": 3.75,
      "colorIndex": 1.174,
      "tier": "T1"
    },
    {
      "id": "hip-53253",
      "sourceId": "HIP 53253",
      "raDeg": 163.373193,
      "decDeg": -58.853265,
      "pmRaMasYr": 79.75,
      "pmDecMasYr": 38.65,
      "parallaxMas": 33.71,
      "mag": 3.78,
      "colorIndex": 0.945,
      "tier": "T1"
    },
    {
      "id": "hip-51232",
      "sourceId": "HIP 51232",
      "raDeg": 156.969771,
      "decDeg": -58.739409,
      "pmRaMasYr": -13.25,
      "pmDecMasYr": 2.21,
      "parallaxMas": 3.13,
      "mag": 3.81,
      "colorIndex": 0.317,
      "tier": "T1"
    },
    {
      "id": "hip-51986",
      "sourceId": "HIP 51986",
      "raDeg": 159.32607,
      "decDeg": -48.225616,
      "pmRaMasYr": -131.48,
      "pmDecMasYr": -1.58,
      "parallaxMas": 37.71,
      "mag": 3.84,
      "colorIndex": 0.3,
      "tier": "T1"
    },
    {
      "id": "hip-55425",
      "sourceId": "HIP 55425",
      "raDeg": 170.251843,
      "decDeg": -54.491014,
      "pmRaMasYr": -35.32,
      "pmDecMasYr": -2.2,
      "parallaxMas": 10.15,
      "mag": 3.9,
      "colorIndex": -0.157,
      "tier": "T1"
    },
    {
      "id": "hip-54463",
      "sourceId": "HIP 54463",
      "raDeg": 167.147482,
      "decDeg": -58.975042,
      "pmRaMasYr": -5.03,
      "pmDecMasYr": 2.09,
      "parallaxMas": 0.55,
      "mag": 3.93,
      "colorIndex": 1.225,
      "tier": "T1"
    },
    {
      "id": "hip-45101",
      "sourceId": "HIP 45101",
      "raDeg": 137.819866,
      "decDeg": -62.317016,
      "pmRaMasYr": -38.04,
      "pmDecMasYr": 15.93,
      "parallaxMas": 6.53,
      "mag": 3.96,
      "colorIndex": -0.18,
      "tier": "T1"
    },
    {
      "id": "hip-44382",
      "sourceId": "HIP 44382",
      "raDeg": 135.611662,
      "decDeg": -66.395844,
      "pmRaMasYr": -2.01,
      "pmDecMasYr": -95.8,
      "parallaxMas": 26.24,
      "mag": 4.0,
      "colorIndex": 0.145,
      "tier": "T1"
    },
    {
      "id": "hip-46974",
      "sourceId": "HIP 46974",
      "raDeg": 143.611096,
      "decDeg": -59.229768,
      "pmRaMasYr": -11.23,
      "pmDecMasYr": 6.02,
      "parallaxMas": 1.65,
      "mag": 4.08,
      "colorIndex": -0.013,
      "tier": "T1"
    },
    {
      "id": "hip-57439",
      "sourceId": "HIP 57439",
      "raDeg": 176.628538,
      "decDeg": -61.178359,
      "pmRaMasYr": -21.85,
      "pmDecMasYr": -16.23,
      "parallaxMas": 7.51,
      "mag": 4.11,
      "colorIndex": 0.895,
      "tier": "T1"
    },
    {
      "id": "hip-52154",
      "sourceId": "HIP 52154",
      "raDeg": 159.826719,
      "decDeg": -55.603279,
      "pmRaMasYr": -18.87,
      "pmDecMasYr": 4.31,
      "parallaxMas": 3.62,
      "mag": 4.29,
      "colorIndex": 1.025,
      "tier": "T1"
    },
    {
      "id": "hip-57669",
      "sourceId": "HIP 57669",
      "raDeg": 177.4212,
      "decDeg": -63.788489,
      "pmRaMasYr": -17.93,
      "pmDecMasYr": 4.44,
      "parallaxMas": 7.1,
      "mag": 4.3,
      "colorIndex": -0.149,
      "tier": "T1"
    },
    {
      "id": "hip-45496",
      "sourceId": "HIP 45496",
      "raDeg": 139.050427,
      "decDeg": -57.541438,
      "pmRaMasYr": -27.77,
      "pmDecMasYr": -14.77,
      "parallaxMas": 6.08,
      "mag": 4.34,
      "colorIndex": 1.602,
      "tier": "T1"
    },
    {
      "id": "hip-47175",
      "sourceId": "HIP 47175",
      "raDeg": 144.206904,
      "decDeg": -49.355129,
      "pmRaMasYr": -130.56,
      "pmDecMasYr": 42.29,
      "parallaxMas": 30.35,
      "mag": 4.34,
      "colorIndex": 0.173,
      "tier": "T1"
    },
    {
      "id": "hip-51849",
      "sourceId": "HIP 51849",
      "raDeg": 158.897144,
      "decDeg": -57.557636,
      "pmRaMasYr": -15.43,
      "pmDecMasYr": -0.16,
      "parallaxMas": 2.37,
      "mag": 4.45,
      "colorIndex": 1.604,
      "tier": "T1"
    },
    {
      "id": "hip-57803",
      "sourceId": "HIP 57803",
      "raDeg": 177.786465,
      "decDeg": -45.173449,
      "pmRaMasYr": -72.42,
      "pmDecMasYr": -8.62,
      "parallaxMas": 7.03,
      "mag": 4.47,
      "colorIndex": 1.283,
      "tier": "T1"
    },
    {
      "id": "hip-50676",
      "sourceId": "HIP 50676",
      "raDeg": 155.228396,
      "decDeg": -56.043224,
      "pmRaMasYr": -18.15,
      "pmDecMasYr": 1.49,
      "parallaxMas": 2.34,
      "mag": 4.5,
      "colorIndex": -0.102,
      "tier": "T1"
    },
    {
      "id": "hip-47391",
      "sourceId": "HIP 47391",
      "raDeg": 144.837671,
      "decDeg": -61.328105,
      "pmRaMasYr": -34.89,
      "pmDecMasYr": 18.6,
      "parallaxMas": 14.57,
      "mag": 4.51,
      "colorIndex": -0.07,
      "tier": "T1"
    },
    {
      "id": "hip-48374",
      "sourceId": "HIP 48374",
      "raDeg": 147.919535,
      "decDeg": -46.547644,
      "pmRaMasYr": -24.41,
      "pmDecMasYr": 9.8,
      "parallaxMas": 3.01,
      "mag": 4.58,
      "colorIndex": 1.172,
      "tier": "T1"
    },
    {
      "id": "hip-52468",
      "sourceId": "HIP 52468",
      "raDeg": 160.884615,
      "decDeg": -60.566627,
      "pmRaMasYr": -15.22,
      "pmDecMasYr": 3.12,
      "parallaxMas": 3.06,
      "mag": 4.58,
      "colorIndex": 1.7,
      "tier": "T1"
    },
    {
      "id": "hip-50555",
      "sourceId": "HIP 50555",
      "raDeg": 154.903188,
      "decDeg": -55.029315,
      "pmRaMasYr": -14.79,
      "pmDecMasYr": 4.03,
      "parallaxMas": 2.19,
      "mag": 4.59,
      "colorIndex": 1.6,
      "tier": "T1"
    },
    {
      "id": "hip-54751",
      "sourceId": "HIP 54751",
      "raDeg": 168.150085,
      "decDeg": -60.317631,
      "pmRaMasYr": -6.23,
      "pmDecMasYr": 2.33,
      "parallaxMas": 0.26,
      "mag": 4.59,
      "colorIndex": 0.541,
      "tier": "T1"
    },
    {
      "id": "hip-54301",
      "sourceId": "HIP 54301",
      "raDeg": 166.63531,
      "decDeg": -62.424137,
      "pmRaMasYr": -36.83,
      "pmDecMasYr": 9.57,
      "parallaxMas": 8.82,
      "mag": 4.62,
      "colorIndex": 0.988,
      "tier": "T1"
    },
    {
      "id": "hip-56480",
      "sourceId": "HIP 56480",
      "raDeg": 173.690466,
      "decDeg": -54.264132,
      "pmRaMasYr": -55.55,
      "pmDecMasYr": 16.64,
      "parallaxMas": 7.04,
      "mag": 4.62,
      "colorIndex": -0.077,
      "tier": "T1"
    },
    {
      "id": "hip-51192",
      "sourceId": "HIP 51192",
      "raDeg": 156.851993,
      "decDeg": -57.638814,
      "pmRaMasYr": -6.71,
      "pmDecMasYr": 3.72,
      "parallaxMas": -0.01,
      "mag": 4.65,
      "colorIndex": 0.474,
      "tier": "T1"
    },
    {
      "id": "hip-52102",
      "sourceId": "HIP 52102",
      "raDeg": 159.687552,
      "decDeg": -59.182999,
      "pmRaMasYr": -14.29,
      "pmDecMasYr": 0.79,
      "parallaxMas": 1.76,
      "mag": 4.69,
      "colorIndex": 1.562,
      "tier": "T1"
    },
    {
      "id": "hip-57581",
      "sourceId": "HIP 57581",
      "raDeg": 177.060373,
      "decDeg": -66.814871,
      "pmRaMasYr": 30.77,
      "pmDecMasYr": -16.25,
      "parallaxMas": 7.55,
      "mag": 4.75,
      "colorIndex": 1.522,
      "tier": "T1"
    },
    {
      "id": "hip-52370",
      "sourceId": "HIP 52370",
      "raDeg": 160.558933,
      "decDeg": -64.466454,
      "pmRaMasYr": -17.75,
      "pmDecMasYr": 11.27,
      "parallaxMas": 7.15,
      "mag": 4.76,
      "colorIndex": -0.139,
      "tier": "T1"
    },
    {
      "id": "hip-45856",
      "sourceId": "HIP 45856",
      "raDeg": 140.236793,
      "decDeg": -62.404633,
      "pmRaMasYr": -14.29,
      "pmDecMasYr": 0.2,
      "parallaxMas": 14.65,
      "mag": 4.79,
      "colorIndex": 0.926,
      "tier": "T1"
    },
    {
      "id": "hip-52502",
      "sourceId": "HIP 52502",
      "raDeg": 161.028905,
      "decDeg": -63.961101,
      "pmRaMasYr": -17.06,
      "pmDecMasYr": 11.97,
      "parallaxMas": 6.74,
      "mag": 4.8,
      "colorIndex": -0.134,
      "tier": "T1"
    },
    {
      "id": "hip-49712",
      "sourceId": "HIP 49712",
      "raDeg": 152.23439,
      "decDeg": -51.811262,
      "pmRaMasYr": -14.6,
      "pmDecMasYr": 0.51,
      "parallaxMas": 3.01,
      "mag": 4.85,
      "colorIndex": -0.12,
      "tier": "T1"
    },
    {
      "id": "hip-52736",
      "sourceId": "HIP 52736",
      "raDeg": 161.713517,
      "decDeg": -64.383497,
      "pmRaMasYr": -18.61,
      "pmDecMasYr": 9.33,
      "parallaxMas": 7.26,
      "mag": 4.87,
      "colorIndex": -0.149,
      "tier": "T1"
    },
    {
      "id": "hip-51523",
      "sourceId": "HIP 51523",
      "raDeg": 157.842645,
      "decDeg": -53.715993,
      "pmRaMasYr": -418.76,
      "pmDecMasYr": 209.46,
      "parallaxMas": 45.72,
      "mag": 4.89,
      "colorIndex": 0.5,
      "tier": "T1"
    },
    {
      "id": "hip-57851",
      "sourceId": "HIP 57851",
      "raDeg": 177.963637,
      "decDeg": -65.205894,
      "pmRaMasYr": -34.37,
      "pmDecMasYr": -6.55,
      "parallaxMas": 9.64,
      "mag": 4.89,
      "colorIndex": -0.123,
      "tier": "T1"
    },
    {
      "id": "hip-56986",
      "sourceId": "HIP 56986",
      "raDeg": 175.223553,
      "decDeg": -62.090104,
      "pmRaMasYr": -15.0,
      "pmDecMasYr": 1.08,
      "parallaxMas": 4.47,
      "mag": 4.93,
      "colorIndex": 1.111,
      "tier": "T1"
    },
    {
      "id": "hip-50847",
      "sourceId": "HIP 50847",
      "raDeg": 155.742414,
      "decDeg": -66.901525,
      "pmRaMasYr": -22.84,
      "pmDecMasYr": 11.04,
      "parallaxMas": 7.59,
      "mag": 4.97,
      "colorIndex": -0.128,
      "tier": "T1"
    },
    {
      "id": "hip-57175",
      "sourceId": "HIP 57175",
      "raDeg": 175.879999,
      "decDeg": -62.489399,
      "pmRaMasYr": -5.85,
      "pmDecMasYr": 1.14,
      "parallaxMas": 1.27,
      "mag": 5.0,
      "colorIndex": 0.784,
      "tier": "T1"
    },
    {
      "id": "hip-46950",
      "sourceId": "HIP 46950",
      "raDeg": 143.536672,
      "decDeg": -51.255282,
      "pmRaMasYr": -8.5,
      "pmDecMasYr": 6.39,
      "parallaxMas": 3.5,
      "mag": 5.01,
      "colorIndex": -0.18,
      "tier": "T1"
    },
    {
      "id": "hip-56862",
      "sourceId": "HIP 56862",
      "raDeg": 174.873471,
      "decDeg": -65.397749,
      "pmRaMasYr": -28.52,
      "pmDecMasYr": -7.01,
      "parallaxMas": 5.81,
      "mag": 5.01,
      "colorIndex": 0.804,
      "tier": "T1"
    },
    {
      "id": "hip-51635",
      "sourceId": "HIP 51635",
      "raDeg": 158.237003,
      "decDeg": -47.003369,
      "pmRaMasYr": -24.04,
      "pmDecMasYr": 6.83,
      "parallaxMas": 3.38,
      "mag": 5.02,
      "colorIndex": 1.045,
      "tier": "T1"
    },
    {
      "id": "hip-49485",
      "sourceId": "HIP 49485",
      "raDeg": 151.546755,
      "decDeg": -47.369865,
      "pmRaMasYr": -10.84,
      "pmDecMasYr": -53.46,
      "parallaxMas": 12.63,
      "mag": 5.06,
      "colorIndex": 0.88,
      "tier": "T1"
    },
    {
      "id": "hip-56243",
      "sourceId": "HIP 56243",
      "raDeg": 172.941971,
      "decDeg": -59.442064,
      "pmRaMasYr": -4.08,
      "pmDecMasYr": 1.14,
      "parallaxMas": 1.01,
      "mag": 5.07,
      "colorIndex": 1.026,
      "tier": "T1"
    },
    {
      "id": "hip-51912",
      "sourceId": "HIP 51912",
      "raDeg": 159.085685,
      "decDeg": -59.564295,
      "pmRaMasYr": -39.9,
      "pmDecMasYr": -39.92,
      "parallaxMas": 12.14,
      "mag": 5.08,
      "colorIndex": 1.172,
      "tier": "T1"
    },
    {
      "id": "hip-46283",
      "sourceId": "HIP 46283",
      "raDeg": 141.574906,
      "decDeg": -53.378936,
      "pmRaMasYr": -19.94,
      "pmDecMasYr": 11.06,
      "parallaxMas": 7.72,
      "mag": 5.09,
      "colorIndex": -0.102,
      "tier": "T1"
    },
    {
      "id": "hip-48224",
      "sourceId": "HIP 48224",
      "raDeg": 147.488173,
      "decDeg": -45.73276,
      "pmRaMasYr": -24.87,
      "pmDecMasYr": 10.07,
      "parallaxMas": 3.81,
      "mag": 5.09,
      "colorIndex": -0.098,
      "tier": "T1"
    },
    {
      "id": "hip-55597",
      "sourceId": "HIP 55597",
      "raDeg": 170.839298,
      "decDeg": -64.954731,
      "pmRaMasYr": -22.59,
      "pmDecMasYr": 7.0,
      "parallaxMas": 6.87,
      "mag": 5.09,
      "colorIndex": -0.061,
      "tier": "T1"
    },
    {
      "id": "hip-54461",
      "sourceId": "HIP 54461",
      "raDeg": 167.14169,
      "decDeg": -61.94718,
      "pmRaMasYr": -5.82,
      "pmDecMasYr": 2.03,
      "parallaxMas": 0.59,
      "mag": 5.11,
      "colorIndex": 0.195,
      "tier": "T1"
    },
    {
      "id": "hip-46914",
      "sourceId": "HIP 46914",
      "raDeg": 143.435666,
      "decDeg": -49.005093,
      "pmRaMasYr": -23.39,
      "pmDecMasYr": 8.78,
      "parallaxMas": 3.4,
      "mag": 5.12,
      "colorIndex": -0.114,
      "tier": "T1"
    },
    {
      "id": "hip-56250",
      "sourceId": "HIP 56250",
      "raDeg": 172.953364,
      "decDeg": -59.515649,
      "pmRaMasYr": -6.59,
      "pmDecMasYr": 0.67,
      "parallaxMas": 0.96,
      "mag": 5.12,
      "colorIndex": 0.432,
      "tier": "T1"
    },
    {
      "id": "hip-52742",
      "sourceId": "HIP 52742",
      "raDeg": 161.739562,
      "decDeg": -56.757191,
      "pmRaMasYr": -21.25,
      "pmDecMasYr": -0.58,
      "parallaxMas": 5.95,
      "mag": 5.14,
      "colorIndex": -0.08,
      "tier": "T1"
    },
    {
      "id": "hip-56656",
      "sourceId": "HIP 56656",
      "raDeg": 174.25334,
      "decDeg": -61.283446,
      "pmRaMasYr": -228.21,
      "pmDecMasYr": 1.73,
      "parallaxMas": 14.11,
      "mag": 5.14,
      "colorIndex": 1.105,
      "tier": "T1"
    },
    {
      "id": "hip-50083",
      "sourceId": "HIP 50083",
      "raDeg": 153.377844,
      "decDeg": -66.372839,
      "pmRaMasYr": -34.35,
      "pmDecMasYr": 11.53,
      "parallaxMas": 10.74,
      "mag": 5.15,
      "colorIndex": 0.217,
      "tier": "T1"
    },
    {
      "id": "hip-56754",
      "sourceId": "HIP 56754",
      "raDeg": 174.530716,
      "decDeg": -61.826555,
      "pmRaMasYr": -62.04,
      "pmDecMasYr": -3.49,
      "parallaxMas": 10.98,
      "mag": 5.15,
      "colorIndex": -0.04,
      "tier": "T1"
    },
    {
      "id": "hip-55779",
      "sourceId": "HIP 55779",
      "raDeg": 171.431517,
      "decDeg": -63.972316,
      "pmRaMasYr": -314.38,
      "pmDecMasYr": -65.52,
      "parallaxMas": 36.46,
      "mag": 5.18,
      "colorIndex": 0.495,
      "tier": "T1"
    },
    {
      "id": "hip-54767",
      "sourceId": "HIP 54767",
      "raDeg": 168.188627,
      "decDeg": -64.169783,
      "pmRaMasYr": -46.98,
      "pmDecMasYr": 5.41,
      "parallaxMas": 10.38,
      "mag": 5.22,
      "colorIndex": -0.082,
      "tier": "T1"
    },
    {
      "id": "hip-55831",
      "sourceId": "HIP 55831",
      "raDeg": 171.647644,
      "decDeg": -61.115171,
      "pmRaMasYr": -13.83,
      "pmDecMasYr": 1.78,
      "parallaxMas": 2.1,
      "mag": 5.22,
      "colorIndex": -0.077,
      "tier": "T1"
    },
    {
      "id": "hip-44337",
      "sourceId": "HIP 44337",
      "raDeg": 135.435722,
      "decDeg": -52.188718,
      "pmRaMasYr": -14.67,
      "pmDecMasYr": 13.53,
      "parallaxMas": 7.46,
      "mag": 5.23,
      "colorIndex": -0.12,
      "tier": "T1"
    },
    {
      "id": "hip-52701",
      "sourceId": "HIP 52701",
      "raDeg": 161.623379,
      "decDeg": -64.263264,
      "pmRaMasYr": -16.98,
      "pmDecMasYr": 9.16,
      "parallaxMas": 7.6,
      "mag": 5.23,
      "colorIndex": -0.077,
      "tier": "T1"
    },
    {
      "id": "hip-45328",
      "sourceId": "HIP 45328",
      "raDeg": 138.575103,
      "decDeg": -55.569701,
      "pmRaMasYr": -32.89,
      "pmDecMasYr": 29.44,
      "parallaxMas": 5.11,
      "mag": 5.26,
      "colorIndex": 0.98,
      "tier": "T1"
    },
    {
      "id": "hip-45631",
      "sourceId": "HIP 45631",
      "raDeg": 139.524543,
      "decDeg": -51.050895,
      "pmRaMasYr": -21.0,
      "pmDecMasYr": 14.83,
      "parallaxMas": 7.57,
      "mag": 5.26,
      "colorIndex": -0.062,
      "tier": "T1"
    },
    {
      "id": "hip-49698",
      "sourceId": "HIP 49698",
      "raDeg": 152.178491,
      "decDeg": -65.815533,
      "pmRaMasYr": -62.86,
      "pmDecMasYr": 38.98,
      "parallaxMas": 9.55,
      "mag": 5.26,
      "colorIndex": 0.973,
      "tier": "T1"
    },
    {
      "id": "hip-53154",
      "sourceId": "HIP 53154",
      "raDeg": 163.128553,
      "decDeg": -57.240414,
      "pmRaMasYr": -6.77,
      "pmDecMasYr": 3.63,
      "parallaxMas": 0.54,
      "mag": 5.26,
      "colorIndex": 0.13,
      "tier": "T1"
    },
    {
      "id": "hip-56573",
      "sourceId": "HIP 56573",
      "raDeg": 173.981482,
      "decDeg": -47.64152,
      "pmRaMasYr": 33.95,
      "pmDecMasYr": -50.42,
      "parallaxMas": 17.24,
      "mag": 5.26,
      "colorIndex": 0.257,
      "tier": "T1"
    },
    {
      "id": "hip-50070",
      "sourceId": "HIP 50070",
      "raDeg": 153.34534,
      "decDeg": -51.232938,
      "pmRaMasYr": -39.7,
      "pmDecMasYr": -13.61,
      "parallaxMas": 20.06,
      "mag": 5.27,
      "colorIndex": 0.257,
      "tier": "T1"
    },
    {
      "id": "hip-51313",
      "sourceId": "HIP 51313",
      "raDeg": 157.219154,
      "decDeg": -64.172285,
      "pmRaMasYr": -15.9,
      "pmDecMasYr": 2.83,
      "parallaxMas": 1.04,
      "mag": 5.27,
      "colorIndex": 1.856,
      "tier": "T1"
    },
    {
      "id": "hip-57371",
      "sourceId": "HIP 57371",
      "raDeg": 176.433349,
      "decDeg": -45.690145,
      "pmRaMasYr": -41.73,
      "pmDecMasYr": 4.8,
      "parallaxMas": 4.17,
      "mag": 5.28,
      "colorIndex": -0.118,
      "tier": "T1"
    },
    {
      "id": "hip-47479",
      "sourceId": "HIP 47479",
      "raDeg": 145.177511,
      "decDeg": -57.983572,
      "pmRaMasYr": -43.84,
      "pmDecMasYr": 7.64,
      "parallaxMas": 14.85,
      "mag": 5.3,
      "colorIndex": 0.195,
      "tier": "T1"
    },
    {
      "id": "hip-52678",
      "sourceId": "HIP 52678",
      "raDeg": 161.569077,
      "decDeg": -64.514586,
      "pmRaMasYr": -15.83,
      "pmDecMasYr": 10.88,
      "parallaxMas": 6.99,
      "mag": 5.33,
      "colorIndex": -0.096,
      "tier": "T1"
    },
    {
      "id": "hip-52405",
      "sourceId": "HIP 52405",
      "raDeg": 160.669058,
      "decDeg": -59.215765,
      "pmRaMasYr": -6.48,
      "pmDecMasYr": 2.32,
      "parallaxMas": 0.48,
      "mag": 5.36,
      "colorIndex": 0.213,
      "tier": "T1"
    },
    {
      "id": "hip-54746",
      "sourceId": "HIP 54746",
      "raDeg": 168.138107,
      "decDeg": -49.101078,
      "pmRaMasYr": -99.28,
      "pmDecMasYr": 33.7,
      "parallaxMas": 20.02,
      "mag": 5.37,
      "colorIndex": 0.175,
      "tier": "T1"
    },
    {
      "id": "hip-57512",
      "sourceId": "HIP 57512",
      "raDeg": 176.829871,
      "decDeg": -57.696547,
      "pmRaMasYr": -25.51,
      "pmDecMasYr": 19.99,
      "parallaxMas": 3.97,
      "mag": 5.42,
      "colorIndex": 1.664,
      "tier": "T1"
    },
    {
      "id": "hip-47204",
      "sourceId": "HIP 47204",
      "raDeg": 144.302817,
      "decDeg": -53.668486,
      "pmRaMasYr": -23.99,
      "pmDecMasYr": -9.13,
      "parallaxMas": 13.95,
      "mag": 5.44,
      "colorIndex": 0.137,
      "tier": "T1"
    },
    {
      "id": "hip-58379",
      "sourceId": "HIP 58379",
      "raDeg": 179.56353,
      "decDeg": -56.317314,
      "pmRaMasYr": -21.56,
      "pmDecMasYr": 1.77,
      "parallaxMas": 5.15,
      "mag": 5.44,
      "colorIndex": -0.062,
      "tier": "T1"
    },
    {
      "id": "hip-46594",
      "sourceId": "HIP 46594",
      "raDeg": 142.521366,
      "decDeg": -51.517193,
      "pmRaMasYr": -18.98,
      "pmDecMasYr": 11.85,
      "parallaxMas": 7.85,
      "mag": 5.45,
      "colorIndex": -0.078,
      "tier": "T1"
    },
    {
      "id": "hip-56700",
      "sourceId": "HIP 56700",
      "raDeg": 174.391876,
      "decDeg": -47.747378,
      "pmRaMasYr": -68.58,
      "pmDecMasYr": 28.07,
      "parallaxMas": 8.98,
      "mag": 5.46,
      "colorIndex": 1.23,
      "tier": "T1"
    },
    {
      "id": "hip-52004",
      "sourceId": "HIP 52004",
      "raDeg": 159.362818,
      "decDeg": -58.733347,
      "pmRaMasYr": -7.46,
      "pmDecMasYr": 3.11,
      "parallaxMas": 0.4,
      "mag": 5.47,
      "colorIndex": 0.5,
      "tier": "T1"
    },
    {
      "id": "hip-56497",
      "sourceId": "HIP 56497",
      "raDeg": 173.737519,
      "decDeg": -49.136947,
      "pmRaMasYr": -172.45,
      "pmDecMasYr": 188.13,
      "parallaxMas": 15.72,
      "mag": 5.5,
      "colorIndex": 1.041,
      "tier": "T1"
    },
    {
      "id": "hip-52221",
      "sourceId": "HIP 52221",
      "raDeg": 160.047765,
      "decDeg": -65.10024,
      "pmRaMasYr": -17.45,
      "pmDecMasYr": 12.86,
      "parallaxMas": 7.0,
      "mag": 5.51,
      "colorIndex": -0.158,
      "tier": "T1"
    },
    {
      "id": "hip-45219",
      "sourceId": "HIP 45219",
      "raDeg": 138.23177,
      "decDeg": -59.413967,
      "pmRaMasYr": 5.55,
      "pmDecMasYr": 15.65,
      "parallaxMas": 6.87,
      "mag": 5.54,
      "colorIndex": 0.846,
      "tier": "T1"
    },
    {
      "id": "hip-47717",
      "sourceId": "HIP 47717",
      "raDeg": 145.926256,
      "decDeg": -53.891362,
      "pmRaMasYr": -67.58,
      "pmDecMasYr": 32.72,
      "parallaxMas": 9.19,
      "mag": 5.56,
      "colorIndex": -0.042,
      "tier": "T1"
    },
    {
      "id": "hip-48310",
      "sourceId": "HIP 48310",
      "raDeg": 147.731659,
      "decDeg": -62.745137,
      "pmRaMasYr": -12.16,
      "pmDecMasYr": 8.46,
      "parallaxMas": 3.4,
      "mag": 5.56,
      "colorIndex": 1.316,
      "tier": "T1"
    },
    {
      "id": "hip-57870",
      "sourceId": "HIP 57870",
      "raDeg": 178.043308,
      "decDeg": -56.987827,
      "pmRaMasYr": -106.9,
      "pmDecMasYr": 35.13,
      "parallaxMas": 9.57,
      "mag": 5.56,
      "colorIndex": 0.069,
      "tier": "T1"
    },
    {
      "id": "hip-51140",
      "sourceId": "HIP 51140",
      "raDeg": 156.703896,
      "decDeg": -54.877314,
      "pmRaMasYr": -13.71,
      "pmDecMasYr": 5.01,
      "parallaxMas": 2.04,
      "mag": 5.58,
      "colorIndex": 1.556,
      "tier": "T1"
    },
    {
      "id": "hip-58326",
      "sourceId": "HIP 58326",
      "raDeg": 179.416826,
      "decDeg": -62.448736,
      "pmRaMasYr": -24.01,
      "pmDecMasYr": -5.19,
      "parallaxMas": 5.45,
      "mag": 5.59,
      "colorIndex": -0.152,
      "tier": "T1"
    },
    {
      "id": "hip-58427",
      "sourceId": "HIP 58427",
      "raDeg": 179.69862,
      "decDeg": -64.339557,
      "pmRaMasYr": -5.98,
      "pmDecMasYr": -1.53,
      "parallaxMas": 1.15,
      "mag": 5.59,
      "colorIndex": 0.174,
      "tier": "T1"
    },
    {
      "id": "hip-45920",
      "sourceId": "HIP 45920",
      "raDeg": 140.458786,
      "decDeg": -55.514871,
      "pmRaMasYr": -64.28,
      "pmDecMasYr": 76.25,
      "parallaxMas": 11.84,
      "mag": 5.61,
      "colorIndex": 0.19,
      "tier": "T1"
    },
    {
      "id": "hip-48348",
      "sourceId": "HIP 48348",
      "raDeg": 147.832342,
      "decDeg": -46.193954,
      "pmRaMasYr": -49.65,
      "pmDecMasYr": 33.82,
      "parallaxMas": 9.74,
      "mag": 5.62,
      "colorIndex": 1.166,
      "tier": "T1"
    },
    {
      "id": "hip-56518",
      "sourceId": "HIP 56518",
      "raDeg": 173.805658,
      "decDeg": -47.372561,
      "pmRaMasYr": -87.27,
      "pmDecMasYr": -7.7,
      "parallaxMas": 5.0,
      "mag": 5.64,
      "colorIndex": 1.682,
      "tier": "T1"
    },
    {
      "id": "hip-50520",
      "sourceId": "HIP 50520",
      "raDeg": 154.771331,
      "decDeg": -64.676288,
      "pmRaMasYr": -35.18,
      "pmDecMasYr": 12.33,
      "parallaxMas": 11.18,
      "mag": 5.66,
      "colorIndex": 0.042,
      "tier": "T1"
    },
    {
      "id": "hip-50609",
      "sourceId": "HIP 50609",
      "raDeg": 155.06968,
      "decDeg": -47.6991,
      "pmRaMasYr": -9.13,
      "pmDecMasYr": 4.0,
      "parallaxMas": 1.21,
      "mag": 5.66,
      "colorIndex": 1.667,
      "tier": "T1"
    },
    {
      "id": "hip-54137",
      "sourceId": "HIP 54137",
      "raDeg": 166.130422,
      "decDeg": -47.679183,
      "pmRaMasYr": -115.47,
      "pmDecMasYr": 32.74,
      "parallaxMas": 11.69,
      "mag": 5.67,
      "colorIndex": 0.256,
      "tier": "T1"
    },
    {
      "id": "hip-57741",
      "sourceId": "HIP 57741",
      "raDeg": 177.613687,
      "decDeg": -62.649383,
      "pmRaMasYr": -5.99,
      "pmDecMasYr": 0.89,
      "parallaxMas": 1.06,
      "mag": 5.68,
      "colorIndex": 0.233,
      "tier": "T1"
    },
    {
      "id": "hip-49934",
      "sourceId": "HIP 49934",
      "raDeg": 152.943633,
      "decDeg": -58.06056,
      "pmRaMasYr": -10.71,
      "pmDecMasYr": 6.63,
      "parallaxMas": 2.52,
      "mag": 5.7,
      "colorIndex": -0.118,
      "tier": "T1"
    },
    {
      "id": "hip-48613",
      "sourceId": "HIP 48613",
      "raDeg": 148.713602,
      "decDeg": -50.243977,
      "pmRaMasYr": -37.02,
      "pmDecMasYr": 7.29,
      "parallaxMas": 10.22,
      "mag": 5.71,
      "colorIndex": 0.006,
      "tier": "T1"
    },
    {
      "id": "hip-48287",
      "sourceId": "HIP 48287",
      "raDeg": 147.674875,
      "decDeg": -46.934002,
      "pmRaMasYr": -38.82,
      "pmDecMasYr": 32.7,
      "parallaxMas": 5.46,
      "mag": 5.72,
      "colorIndex": 1.085,
      "tier": "T1"
    },
    {
      "id": "hip-48561",
      "sourceId": "HIP 48561",
      "raDeg": 148.573619,
      "decDeg": -45.283527,
      "pmRaMasYr": -17.2,
      "pmDecMasYr": 4.42,
      "parallaxMas": 3.86,
      "mag": 5.72,
      "colorIndex": -0.114,
      "tier": "T1"
    },
    {
      "id": "hip-45962",
      "sourceId": "HIP 45962",
      "raDeg": 140.599979,
      "decDeg": -46.047502,
      "pmRaMasYr": -3.02,
      "pmDecMasYr": 23.71,
      "parallaxMas": 5.72,
      "mag": 5.74,
      "colorIndex": 0.903,
      "tier": "T1"
    },
    {
      "id": "hip-52487",
      "sourceId": "HIP 52487",
      "raDeg": 160.963394,
      "decDeg": -64.249052,
      "pmRaMasYr": -16.35,
      "pmDecMasYr": 4.05,
      "parallaxMas": 3.23,
      "mag": 5.74,
      "colorIndex": 0.012,
      "tier": "T1"
    },
    {
      "id": "hip-54829",
      "sourceId": "HIP 54829",
      "raDeg": 168.378296,
      "decDeg": -59.619317,
      "pmRaMasYr": -7.52,
      "pmDecMasYr": -0.57,
      "parallaxMas": 1.79,
      "mag": 5.74,
      "colorIndex": -0.106,
      "tier": "T1"
    },
    {
      "id": "hip-54840",
      "sourceId": "HIP 54840",
      "raDeg": 168.414207,
      "decDeg": -53.231903,
      "pmRaMasYr": -16.39,
      "pmDecMasYr": 37.23,
      "parallaxMas": 7.31,
      "mag": 5.75,
      "colorIndex": 1.309,
      "tier": "T1"
    },
    {
      "id": "hip-51561",
      "sourceId": "HIP 51561",
      "raDeg": 157.98937,
      "decDeg": -45.066714,
      "pmRaMasYr": -15.4,
      "pmDecMasYr": 1.41,
      "parallaxMas": 7.04,
      "mag": 5.76,
      "colorIndex": -0.194,
      "tier": "T1"
    },
    {
      "id": "hip-46225",
      "sourceId": "HIP 46225",
      "raDeg": 141.364074,
      "decDeg": -61.950612,
      "pmRaMasYr": -115.54,
      "pmDecMasYr": 55.95,
      "parallaxMas": 13.79,
      "mag": 5.77,
      "colorIndex": 0.137,
      "tier": "T1"
    },
    {
      "id": "hip-45122",
      "sourceId": "HIP 45122",
      "raDeg": 137.889121,
      "decDeg": -46.583929,
      "pmRaMasYr": -7.17,
      "pmDecMasYr": 7.65,
      "parallaxMas": 2.85,
      "mag": 5.78,
      "colorIndex": -0.218,
      "tier": "T1"
    },
    {
      "id": "hip-50078",
      "sourceId": "HIP 50078",
      "raDeg": 153.366851,
      "decDeg": -51.755805,
      "pmRaMasYr": -53.27,
      "pmDecMasYr": 6.95,
      "parallaxMas": 10.25,
      "mag": 5.78,
      "colorIndex": 0.136,
      "tier": "T1"
    },
    {
      "id": "hip-48339",
      "sourceId": "HIP 48339",
      "raDeg": 147.80014,
      "decDeg": -59.425673,
      "pmRaMasYr": 28.4,
      "pmDecMasYr": -41.59,
      "parallaxMas": 4.37,
      "mag": 5.79,
      "colorIndex": 1.354,
      "tier": "T1"
    },
    {
      "id": "hip-44256",
      "sourceId": "HIP 44256",
      "raDeg": 135.190613,
      "decDeg": -60.963847,
      "pmRaMasYr": -4.42,
      "pmDecMasYr": 7.76,
      "parallaxMas": 2.59,
      "mag": 5.8,
      "colorIndex": 1.211,
      "tier": "T1"
    },
    {
      "id": "hip-47498",
      "sourceId": "HIP 47498",
      "raDeg": 145.258762,
      "decDeg": -57.259441,
      "pmRaMasYr": 76.24,
      "pmDecMasYr": -41.64,
      "parallaxMas": 9.0,
      "mag": 5.8,
      "colorIndex": 1.083,
      "tier": "T1"
    },
    {
      "id": "hip-50493",
      "sourceId": "HIP 50493",
      "raDeg": 154.658994,
      "decDeg": -56.110675,
      "pmRaMasYr": -239.33,
      "pmDecMasYr": 115.9,
      "parallaxMas": 27.91,
      "mag": 5.8,
      "colorIndex": 0.481,
      "tier": "T1"
    },
    {
      "id": "hip-55849",
      "sourceId": "HIP 55849",
      "raDeg": 171.697103,
      "decDeg": -53.159956,
      "pmRaMasYr": -40.94,
      "pmDecMasYr": 16.76,
      "parallaxMas": 5.22,
      "mag": 5.8,
      "colorIndex": 0.517,
      "tier": "T1"
    },
    {
      "id": "hip-55581",
      "sourceId": "HIP 55581",
      "raDeg": 170.784022,
      "decDeg": -56.779369,
      "pmRaMasYr": -31.63,
      "pmDecMasYr": 5.72,
      "parallaxMas": 4.99,
      "mag": 5.82,
      "colorIndex": -0.004,
      "tier": "T1"
    },
    {
      "id": "hip-45675",
      "sourceId": "HIP 45675",
      "raDeg": 139.676506,
      "decDeg": -51.56066,
      "pmRaMasYr": -5.22,
      "pmDecMasYr": 3.5,
      "parallaxMas": 0.17,
      "mag": 5.83,
      "colorIndex": 0.474,
      "tier": "T1"
    },
    {
      "id": "hip-56606",
      "sourceId": "HIP 56606",
      "raDeg": 174.093254,
      "decDeg": -61.052437,
      "pmRaMasYr": -12.94,
      "pmDecMasYr": 1.7,
      "parallaxMas": 2.23,
      "mag": 5.84,
      "colorIndex": -0.102,
      "tier": "T1"
    },
    {
      "id": "hip-52922",
      "sourceId": "HIP 52922",
      "raDeg": 162.351902,
      "decDeg": -59.323778,
      "pmRaMasYr": -16.79,
      "pmDecMasYr": -5.94,
      "parallaxMas": 3.82,
      "mag": 5.85,
      "colorIndex": 0.008,
      "tier": "T1"
    },
    {
      "id": "hip-46620",
      "sourceId": "HIP 46620",
      "raDeg": 142.597722,
      "decDeg": -58.361904,
      "pmRaMasYr": -28.81,
      "pmDecMasYr": 26.67,
      "parallaxMas": 3.08,
      "mag": 5.88,
      "colorIndex": 1.676,
      "tier": "T1"
    },
    {
      "id": "hip-52043",
      "sourceId": "HIP 52043",
      "raDeg": 159.511091,
      "decDeg": -57.256311,
      "pmRaMasYr": -15.58,
      "pmDecMasYr": 0.72,
      "parallaxMas": 2.55,
      "mag": 5.89,
      "colorIndex": -0.128,
      "tier": "T1"
    },
    {
      "id": "hip-56287",
      "sourceId": "HIP 56287",
      "raDeg": 173.083319,
      "decDeg": -66.961835,
      "pmRaMasYr": -0.1,
      "pmDecMasYr": 4.68,
      "parallaxMas": 10.94,
      "mag": 5.89,
      "colorIndex": 1.136,
      "tier": "T1"
    },
    {
      "id": "hip-58103",
      "sourceId": "HIP 58103",
      "raDeg": 178.750095,
      "decDeg": -63.279179,
      "pmRaMasYr": -8.83,
      "pmDecMasYr": -0.51,
      "parallaxMas": 1.27,
      "mag": 5.89,
      "colorIndex": 0.21,
      "tier": "T1"
    },
    {
      "id": "hip-46460",
      "sourceId": "HIP 46460",
      "raDeg": 142.127491,
      "decDeg": -66.701989,
      "pmRaMasYr": -34.47,
      "pmDecMasYr": 45.82,
      "parallaxMas": 12.17,
      "mag": 5.9,
      "colorIndex": 0.012,
      "tier": "T1"
    },
    {
      "id": "hip-53530",
      "sourceId": "HIP 53530",
      "raDeg": 164.282841,
      "decDeg": -50.765049,
      "pmRaMasYr": -37.55,
      "pmDecMasYr": 12.92,
      "parallaxMas": 10.3,
      "mag": 5.9,
      "colorIndex": 0.173,
      "tier": "T1"
    },
    {
      "id": "hip-46482",
      "sourceId": "HIP 46482",
      "raDeg": 142.19661,
      "decDeg": -62.273203,
      "pmRaMasYr": -65.4,
      "pmDecMasYr": 28.42,
      "parallaxMas": 6.76,
      "mag": 5.91,
      "colorIndex": 1.102,
      "tier": "T1"
    },
    {
      "id": "hip-45270",
      "sourceId": "HIP 45270",
      "raDeg": 138.393647,
      "decDeg": -47.33844,
      "pmRaMasYr": -25.0,
      "pmDecMasYr": 13.35,
      "parallaxMas": 5.88,
      "mag": 5.92,
      "colorIndex": -0.051,
      "tier": "T1"
    },
    {
      "id": "hip-49164",
      "sourceId": "HIP 49164",
      "raDeg": 150.500438,
      "decDeg": -60.4209,
      "pmRaMasYr": -7.42,
      "pmDecMasYr": 3.9,
      "parallaxMas": 1.02,
      "mag": 5.93,
      "colorIndex": 0.263,
      "tier": "T1"
    },
    {
      "id": "hip-50993",
      "sourceId": "HIP 50993",
      "raDeg": 156.24792,
      "decDeg": -58.576318,
      "pmRaMasYr": -74.09,
      "pmDecMasYr": 6.12,
      "parallaxMas": 10.98,
      "mag": 5.93,
      "colorIndex": 0.315,
      "tier": "T1"
    },
    {
      "id": "hip-53394",
      "sourceId": "HIP 53394",
      "raDeg": 163.821929,
      "decDeg": -60.517208,
      "pmRaMasYr": -36.09,
      "pmDecMasYr": 84.3,
      "parallaxMas": 10.66,
      "mag": 5.93,
      "colorIndex": 1.065,
      "tier": "T1"
    },
    {
      "id": "hip-48527",
      "sourceId": "HIP 48527",
      "raDeg": 148.458796,
      "decDeg": -51.146715,
      "pmRaMasYr": -13.68,
      "pmDecMasYr": 0.55,
      "parallaxMas": 1.91,
      "mag": 5.95,
      "colorIndex": -0.152,
      "tier": "T1"
    },
    {
      "id": "hip-53334",
      "sourceId": "HIP 53334",
      "raDeg": 163.623323,
      "decDeg": -61.826613,
      "pmRaMasYr": 4.92,
      "pmDecMasYr": -3.85,
      "parallaxMas": 1.96,
      "mag": 5.95,
      "colorIndex": 1.736,
      "tier": "T1"
    },
    {
      "id": "hip-56970",
      "sourceId": "HIP 56970",
      "raDeg": 175.177051,
      "decDeg": -53.968549,
      "pmRaMasYr": -10.83,
      "pmDecMasYr": -23.94,
      "parallaxMas": 3.06,
      "mag": 5.95,
      "colorIndex": 1.67,
      "tier": "T1"
    },
    {
      "id": "hip-52127",
      "sourceId": "HIP 52127",
      "raDeg": 159.74877,
      "decDeg": -58.816886,
      "pmRaMasYr": -76.65,
      "pmDecMasYr": 13.1,
      "parallaxMas": 5.03,
      "mag": 5.96,
      "colorIndex": 1.692,
      "tier": "T1"
    },
    {
      "id": "hip-51623",
      "sourceId": "HIP 51623",
      "raDeg": 158.199236,
      "decDeg": -58.66675,
      "pmRaMasYr": -6.54,
      "pmDecMasYr": 2.16,
      "parallaxMas": 0.29,
      "mag": 5.98,
      "colorIndex": 0.29,
      "tier": "T1"
    },
    {
      "id": "hip-52827",
      "sourceId": "HIP 52827",
      "raDeg": 162.022566,
      "decDeg": -59.919169,
      "pmRaMasYr": -7.58,
      "pmDecMasYr": 2.71,
      "parallaxMas": -0.01,
      "mag": 5.98,
      "colorIndex": 0.274,
      "tier": "T1"
    },
    {
      "id": "hip-46101",
      "sourceId": "HIP 46101",
      "raDeg": 141.022899,
      "decDeg": -61.648787,
      "pmRaMasYr": -0.82,
      "pmDecMasYr": -47.52,
      "parallaxMas": 9.67,
      "mag": 5.99,
      "colorIndex": 1.06,
      "tier": "T1"
    },
    {
      "id": "hip-47559",
      "sourceId": "HIP 47559",
      "raDeg": 145.44975,
      "decDeg": -55.21377,
      "pmRaMasYr": -12.34,
      "pmDecMasYr": 3.26,
      "parallaxMas": 1.21,
      "mag": 5.99,
      "colorIndex": -0.119,
      "tier": "T1"
    },
    {
      "id": "hip-55280",
      "sourceId": "HIP 55280",
      "raDeg": 169.820181,
      "decDeg": -64.582597,
      "pmRaMasYr": -301.28,
      "pmDecMasYr": 43.9,
      "parallaxMas": 26.72,
      "mag": 5.99,
      "colorIndex": 0.471,
      "tier": "T1"
    },
    {
      "id": "hip-51194",
      "sourceId": "HIP 51194",
      "raDeg": 156.855831,
      "decDeg": -65.704714,
      "pmRaMasYr": -81.88,
      "pmDecMasYr": 20.57,
      "parallaxMas": 14.22,
      "mag": 6.0,
      "colorIndex": 0.091,
      "tier": "T1"
    },
    {
      "id": "hip-45418",
      "sourceId": "HIP 45418",
      "raDeg": 138.823576,
      "decDeg": -58.38838,
      "pmRaMasYr": -17.25,
      "pmDecMasYr": 1.14,
      "parallaxMas": 6.24,
      "mag": 6.02,
      "colorIndex": -0.101,
      "tier": "T1"
    },
    {
      "id": "hip-51560",
      "sourceId": "HIP 51560",
      "raDeg": 157.986059,
      "decDeg": -45.069656,
      "pmRaMasYr": -19.96,
      "pmDecMasYr": -1.7,
      "parallaxMas": 6.83,
      "mag": 6.04,
      "colorIndex": -0.096,
      "tier": "T1"
    },
    {
      "id": "hip-58453",
      "sourceId": "HIP 58453",
      "raDeg": 179.795322,
      "decDeg": -51.696748,
      "pmRaMasYr": -15.46,
      "pmDecMasYr": -5.21,
      "parallaxMas": 3.84,
      "mag": 6.04,
      "colorIndex": 1.277,
      "tier": "T1"
    },
    {
      "id": "hip-46093",
      "sourceId": "HIP 46093",
      "raDeg": 140.997245,
      "decDeg": -51.737091,
      "pmRaMasYr": -4.71,
      "pmDecMasYr": 4.4,
      "parallaxMas": 0.57,
      "mag": 6.05,
      "colorIndex": 0.528,
      "tier": "T1"
    },
    {
      "id": "hip-46328",
      "sourceId": "HIP 46328",
      "raDeg": 141.684088,
      "decDeg": -64.929857,
      "pmRaMasYr": -63.33,
      "pmDecMasYr": 64.17,
      "parallaxMas": 14.65,
      "mag": 6.05,
      "colorIndex": 0.147,
      "tier": "T1"
    },
    {
      "id": "hip-48119",
      "sourceId": "HIP 48119",
      "raDeg": 147.166913,
      "decDeg": -56.411926,
      "pmRaMasYr": -58.39,
      "pmDecMasYr": 14.77,
      "parallaxMas": 9.82,
      "mag": 6.05,
      "colorIndex": 0.937,
      "tier": "T1"
    },
    {
      "id": "hip-58041",
      "sourceId": "HIP 58041",
      "raDeg": 178.547965,
      "decDeg": -57.410191,
      "pmRaMasYr": -9.67,
      "pmDecMasYr": -2.82,
      "parallaxMas": 2.38,
      "mag": 6.05,
      "colorIndex": 0.05,
      "tier": "T1"
    },
    {
      "id": "hip-48835",
      "sourceId": "HIP 48835",
      "raDeg": 149.427524,
      "decDeg": -48.41407,
      "pmRaMasYr": -9.34,
      "pmDecMasYr": -1.84,
      "parallaxMas": 0.86,
      "mag": 6.06,
      "colorIndex": -0.127,
      "tier": "T1"
    },
    {
      "id": "hip-49926",
      "sourceId": "HIP 49926",
      "raDeg": 152.897866,
      "decDeg": -58.827827,
      "pmRaMasYr": -24.57,
      "pmDecMasYr": 26.79,
      "parallaxMas": 4.32,
      "mag": 6.07,
      "colorIndex": 1.647,
      "tier": "T1"
    },
    {
      "id": "hip-50044",
      "sourceId": "HIP 50044",
      "raDeg": 153.254852,
      "decDeg": -59.918094,
      "pmRaMasYr": -15.31,
      "pmDecMasYr": 2.6,
      "parallaxMas": 1.65,
      "mag": 6.07,
      "colorIndex": -0.072,
      "tier": "T1"
    },
    {
      "id": "hip-54294",
      "sourceId": "HIP 54294",
      "raDeg": 166.622081,
      "decDeg": -58.675036,
      "pmRaMasYr": -10.06,
      "pmDecMasYr": 5.86,
      "parallaxMas": 2.66,
      "mag": 6.07,
      "colorIndex": 1.21,
      "tier": "T1"
    },
    {
      "id": "hip-51676",
      "sourceId": "HIP 51676",
      "raDeg": 158.355822,
      "decDeg": -58.190157,
      "pmRaMasYr": -7.75,
      "pmDecMasYr": 3.39,
      "parallaxMas": 0.24,
      "mag": 6.09,
      "colorIndex": 0.325,
      "tier": "T1"
    },
    {
      "id": "hip-44708",
      "sourceId": "HIP 44708",
      "raDeg": 136.641836,
      "decDeg": -55.802429,
      "pmRaMasYr": -9.56,
      "pmDecMasYr": 7.04,
      "parallaxMas": 2.75,
      "mag": 6.1,
      "colorIndex": -0.132,
      "tier": "T1"
    },
    {
      "id": "hip-51245",
      "sourceId": "HIP 51245",
      "raDeg": 157.008661,
      "decDeg": -49.405692,
      "pmRaMasYr": 19.1,
      "pmDecMasYr": -44.93,
      "parallaxMas": 3.54,
      "mag": 6.1,
      "colorIndex": 1.506,
      "tier": "T1"
    },
    {
      "id": "hip-57211",
      "sourceId": "HIP 57211",
      "raDeg": 175.970101,
      "decDeg": -62.878243,
      "pmRaMasYr": 13.47,
      "pmDecMasYr": -15.26,
      "parallaxMas": 8.23,
      "mag": 6.1,
      "colorIndex": 0.063,
      "tier": "T1"
    },
    {
      "id": "hip-49259",
      "sourceId": "HIP 49259",
      "raDeg": 150.835853,
      "decDeg": -46.636165,
      "pmRaMasYr": -28.39,
      "pmDecMasYr": -10.77,
      "parallaxMas": 10.85,
      "mag": 6.11,
      "colorIndex": 0.041,
      "tier": "T1"
    },
    {
      "id": "hip-54185",
      "sourceId": "HIP 54185",
      "raDeg": 166.267265,
      "decDeg": -49.392326,
      "pmRaMasYr": -36.36,
      "pmDecMasYr": 11.03,
      "parallaxMas": 6.34,
      "mag": 6.11,
      "colorIndex": -0.019,
      "tier": "T1"
    },
    {
      "id": "hip-54783",
      "sourceId": "HIP 54783",
      "raDeg": 168.236416,
      "decDeg": -49.736105,
      "pmRaMasYr": -26.0,
      "pmDecMasYr": 6.36,
      "parallaxMas": 4.29,
      "mag": 6.12,
      "colorIndex": 1.055,
      "tier": "T1"
    },
    {
      "id": "hip-48799",
      "sourceId": "HIP 48799",
      "raDeg": 149.295623,
      "decDeg": -52.638793,
      "pmRaMasYr": -8.83,
      "pmDecMasYr": 4.11,
      "parallaxMas": 0.95,
      "mag": 6.13,
      "colorIndex": -0.115,
      "tier": "T1"
    },
    {
      "id": "hip-45615",
      "sourceId": "HIP 45615",
      "raDeg": 139.465276,
      "decDeg": -67.050899,
      "pmRaMasYr": -6.57,
      "pmDecMasYr": 12.72,
      "parallaxMas": 2.4,
      "mag": 6.14,
      "colorIndex": 1.254,
      "tier": "T1"
    },
    {
      "id": "hip-49281",
      "sourceId": "HIP 49281",
      "raDeg": 150.892248,
      "decDeg": -61.88405,
      "pmRaMasYr": -17.73,
      "pmDecMasYr": 4.23,
      "parallaxMas": 1.88,
      "mag": 6.14,
      "colorIndex": -0.032,
      "tier": "T1"
    },
    {
      "id": "hip-47694",
      "sourceId": "HIP 47694",
      "raDeg": 145.865012,
      "decDeg": -51.228156,
      "pmRaMasYr": -16.02,
      "pmDecMasYr": 8.37,
      "parallaxMas": 2.39,
      "mag": 6.15,
      "colorIndex": -0.098,
      "tier": "T1"
    },
    {
      "id": "hip-53771",
      "sourceId": "HIP 53771",
      "raDeg": 165.034745,
      "decDeg": -51.817806,
      "pmRaMasYr": -64.0,
      "pmDecMasYr": 2.81,
      "parallaxMas": 16.7,
      "mag": 6.15,
      "colorIndex": 0.188,
      "tier": "T1"
    },
    {
      "id": "hip-49994",
      "sourceId": "HIP 49994",
      "raDeg": 153.095722,
      "decDeg": -52.163352,
      "pmRaMasYr": -52.74,
      "pmDecMasYr": 45.23,
      "parallaxMas": 9.75,
      "mag": 6.16,
      "colorIndex": 1.168,
      "tier": "T1"
    },
    {
      "id": "hip-50232",
      "sourceId": "HIP 50232",
      "raDeg": 153.819386,
      "decDeg": -54.974215,
      "pmRaMasYr": -13.49,
      "pmDecMasYr": 3.23,
      "parallaxMas": 2.29,
      "mag": 6.16,
      "colorIndex": -0.155,
      "tier": "T1"
    },
    {
      "id": "hip-53701",
      "sourceId": "HIP 53701",
      "raDeg": 164.808524,
      "decDeg": -61.320744,
      "pmRaMasYr": -28.7,
      "pmDecMasYr": 1.94,
      "parallaxMas": 8.99,
      "mag": 6.16,
      "colorIndex": -0.064,
      "tier": "T1"
    },
    {
      "id": "hip-54082",
      "sourceId": "HIP 54082",
      "raDeg": 166.001035,
      "decDeg": -57.955333,
      "pmRaMasYr": -18.37,
      "pmDecMasYr": 0.65,
      "parallaxMas": 1.1,
      "mag": 6.16,
      "colorIndex": -0.167,
      "tier": "T1"
    },
    {
      "id": "hip-47145",
      "sourceId": "HIP 47145",
      "raDeg": 144.105889,
      "decDeg": -48.751161,
      "pmRaMasYr": -8.01,
      "pmDecMasYr": -7.7,
      "parallaxMas": 13.8,
      "mag": 6.18,
      "colorIndex": 0.277,
      "tier": "T1"
    },
    {
      "id": "hip-47172",
      "sourceId": "HIP 47172",
      "raDeg": 144.193379,
      "decDeg": -52.943906,
      "pmRaMasYr": -125.12,
      "pmDecMasYr": 96.95,
      "parallaxMas": 8.4,
      "mag": 6.18,
      "colorIndex": 1.051,
      "tier": "T1"
    },
    {
      "id": "hip-49233",
      "sourceId": "HIP 49233",
      "raDeg": 150.749791,
      "decDeg": -60.178686,
      "pmRaMasYr": -6.89,
      "pmDecMasYr": 4.6,
      "parallaxMas": 1.01,
      "mag": 6.18,
      "colorIndex": 0.175,
      "tier": "T1"
    },
    {
      "id": "hip-45002",
      "sourceId": "HIP 45002",
      "raDeg": 137.488133,
      "decDeg": -52.082993,
      "pmRaMasYr": -91.72,
      "pmDecMasYr": 54.65,
      "parallaxMas": 10.73,
      "mag": 6.19,
      "colorIndex": 1.023,
      "tier": "T1"
    },
    {
      "id": "hip-51425",
      "sourceId": "HIP 51425",
      "raDeg": 157.536719,
      "decDeg": -66.984667,
      "pmRaMasYr": -17.36,
      "pmDecMasYr": 5.24,
      "parallaxMas": 2.64,
      "mag": 6.19,
      "colorIndex": -0.004,
      "tier": "T1"
    },
    {
      "id": "hip-49137",
      "sourceId": "HIP 49137",
      "raDeg": 150.419689,
      "decDeg": -53.364116,
      "pmRaMasYr": -16.56,
      "pmDecMasYr": 0.47,
      "parallaxMas": 2.26,
      "mag": 6.2,
      "colorIndex": -0.137,
      "tier": "T1"
    },
    {
      "id": "hip-49160",
      "sourceId": "HIP 49160",
      "raDeg": 150.492043,
      "decDeg": -57.349845,
      "pmRaMasYr": -38.39,
      "pmDecMasYr": 22.82,
      "parallaxMas": 4.33,
      "mag": 6.2,
      "colorIndex": 1.108,
      "tier": "T1"
    },
    {
      "id": "hip-50332",
      "sourceId": "HIP 50332",
      "raDeg": 154.167386,
      "decDeg": -51.204664,
      "pmRaMasYr": -39.92,
      "pmDecMasYr": 11.71,
      "parallaxMas": 4.66,
      "mag": 6.2,
      "colorIndex": 1.435,
      "tier": "T1"
    },
    {
      "id": "hip-46067",
      "sourceId": "HIP 46067",
      "raDeg": 140.915715,
      "decDeg": -46.908769,
      "pmRaMasYr": -19.27,
      "pmDecMasYr": 7.45,
      "parallaxMas": 2.89,
      "mag": 6.21,
      "colorIndex": -0.093,
      "tier": "T1"
    },
    {
      "id": "hip-47913",
      "sourceId": "HIP 47913",
      "raDeg": 146.482594,
      "decDeg": -58.794,
      "pmRaMasYr": -102.23,
      "pmDecMasYr": 70.89,
      "parallaxMas": 12.36,
      "mag": 6.22,
      "colorIndex": 0.461,
      "tier": "T1"
    },
    {
      "id": "hip-50287",
      "sourceId": "HIP 50287",
      "raDeg": 154.013567,
      "decDeg": -59.903436,
      "pmRaMasYr": -39.12,
      "pmDecMasYr": 10.59,
      "parallaxMas": 12.07,
      "mag": 6.22,
      "colorIndex": 0.194,
      "tier": "T1"
    },
    {
      "id": "hip-49394",
      "sourceId": "HIP 49394",
      "raDeg": 151.257762,
      "decDeg": -51.313648,
      "pmRaMasYr": -29.55,
      "pmDecMasYr": 11.27,
      "parallaxMas": 6.13,
      "mag": 6.23,
      "colorIndex": -0.054,
      "tier": "T1"
    },
    {
      "id": "hip-56550",
      "sourceId": "HIP 56550",
      "raDeg": 173.926433,
      "decDeg": -61.287874,
      "pmRaMasYr": -7.0,
      "pmDecMasYr": 1.54,
      "parallaxMas": 0.74,
      "mag": 6.23,
      "colorIndex": 0.131,
      "tier": "T1"
    },
    {
      "id": "hip-54708",
      "sourceId": "HIP 54708",
      "raDeg": 168.014983,
      "decDeg": -58.423354,
      "pmRaMasYr": -49.73,
      "pmDecMasYr": -0.76,
      "parallaxMas": 4.43,
      "mag": 6.24,
      "colorIndex": 1.495,
      "tier": "T1"
    },
    {
      "id": "hip-45413",
      "sourceId": "HIP 45413",
      "raDeg": 138.811005,
      "decDeg": -45.555493,
      "pmRaMasYr": -7.9,
      "pmDecMasYr": -2.0,
      "parallaxMas": 1.8,
      "mag": 6.25,
      "colorIndex": -0.07,
      "tier": "T1"
    },
    {
      "id": "hip-51732",
      "sourceId": "HIP 51732",
      "raDeg": 158.553009,
      "decDeg": -60.987629,
      "pmRaMasYr": -8.72,
      "pmDecMasYr": -0.22,
      "parallaxMas": 3.93,
      "mag": 6.25,
      "colorIndex": 1.399,
      "tier": "T1"
    },
    {
      "id": "hip-52679",
      "sourceId": "HIP 52679",
      "raDeg": 161.571322,
      "decDeg": -60.602893,
      "pmRaMasYr": -43.82,
      "pmDecMasYr": 8.38,
      "parallaxMas": 8.93,
      "mag": 6.26,
      "colorIndex": 0.038,
      "tier": "T1"
    },
    {
      "id": "hip-53231",
      "sourceId": "HIP 53231",
      "raDeg": 163.33826,
      "decDeg": -58.893461,
      "pmRaMasYr": -13.23,
      "pmDecMasYr": 3.27,
      "parallaxMas": 2.07,
      "mag": 6.26,
      "colorIndex": -0.104,
      "tier": "T1"
    },
    {
      "id": "hip-57322",
      "sourceId": "HIP 57322",
      "raDeg": 176.302735,
      "decDeg": -49.069869,
      "pmRaMasYr": -22.97,
      "pmDecMasYr": 10.87,
      "parallaxMas": 6.26,
      "mag": 6.26,
      "colorIndex": 1.174,
      "tier": "T1"
    },
    {
      "id": "hip-58242",
      "sourceId": "HIP 58242",
      "raDeg": 179.183433,
      "decDeg": -47.072436,
      "pmRaMasYr": -126.5,
      "pmDecMasYr": 23.1,
      "parallaxMas": 18.52,
      "mag": 6.26,
      "colorIndex": 0.407,
      "tier": "T1"
    },
    {
      "id": "hip-46045",
      "sourceId": "HIP 46045",
      "raDeg": 140.855739,
      "decDeg": -48.286957,
      "pmRaMasYr": -12.14,
      "pmDecMasYr": 6.22,
      "parallaxMas": 2.34,
      "mag": 6.27,
      "colorIndex": -0.144,
      "tier": "T1"
    },
    {
      "id": "hip-46737",
      "sourceId": "HIP 46737",
      "raDeg": 142.887705,
      "decDeg": -66.719045,
      "pmRaMasYr": -17.93,
      "pmDecMasYr": 7.78,
      "parallaxMas": 4.64,
      "mag": 6.27,
      "colorIndex": 1.348,
      "tier": "T1"
    },
    {
      "id": "hip-54718",
      "sourceId": "HIP 54718",
      "raDeg": 168.042687,
      "decDeg": -46.266775,
      "pmRaMasYr": -51.71,
      "pmDecMasYr": 5.58,
      "parallaxMas": 10.11,
      "mag": 6.27,
      "colorIndex": 0.155,
      "tier": "T1"
    },
    {
      "id": "hip-45742",
      "sourceId": "HIP 45742",
      "raDeg": 139.885366,
      "decDeg": -55.186491,
      "pmRaMasYr": -12.61,
      "pmDecMasYr": 8.23,
      "parallaxMas": 0.95,
      "mag": 6.28,
      "colorIndex": -0.099,
      "tier": "T1"
    },
    {
      "id": "hip-54264",
      "sourceId": "HIP 54264",
      "raDeg": 166.523921,
      "decDeg": -51.212744,
      "pmRaMasYr": -0.53,
      "pmDecMasYr": -72.33,
      "parallaxMas": 7.92,
      "mag": 6.28,
      "colorIndex": 0.943,
      "tier": "T1"
    },
    {
      "id": "hip-56201",
      "sourceId": "HIP 56201",
      "raDeg": 172.812719,
      "decDeg": -61.278468,
      "pmRaMasYr": -6.41,
      "pmDecMasYr": 2.0,
      "parallaxMas": 0.7,
      "mag": 6.28,
      "colorIndex": 0.473,
      "tier": "T1"
    },
    {
      "id": "hip-52797",
      "sourceId": "HIP 52797",
      "raDeg": 161.910039,
      "decDeg": -57.467418,
      "pmRaMasYr": -11.94,
      "pmDecMasYr": 2.78,
      "parallaxMas": 1.18,
      "mag": 6.29,
      "colorIndex": 1.673,
      "tier": "T1"
    },
    {
      "id": "hip-53100",
      "sourceId": "HIP 53100",
      "raDeg": 162.945542,
      "decDeg": -57.272315,
      "pmRaMasYr": -50.89,
      "pmDecMasYr": -0.1,
      "parallaxMas": 5.4,
      "mag": 6.29,
      "colorIndex": 0.226,
      "tier": "T1"
    },
    {
      "id": "hip-46049",
      "sourceId": "HIP 46049",
      "raDeg": 140.863889,
      "decDeg": -60.30233,
      "pmRaMasYr": -10.28,
      "pmDecMasYr": 6.61,
      "parallaxMas": 1.44,
      "mag": 6.3,
      "colorIndex": 1.477,
      "tier": "T1"
    },
    {
      "id": "hip-55068",
      "sourceId": "HIP 55068",
      "raDeg": 169.116419,
      "decDeg": -45.880179,
      "pmRaMasYr": -139.84,
      "pmDecMasYr": 68.68,
      "parallaxMas": 18.05,
      "mag": 6.3,
      "colorIndex": 0.403,
      "tier": "T1"
    },
    {
      "id": "hip-54291",
      "sourceId": "HIP 54291",
      "raDeg": 166.614857,
      "decDeg": -50.956743,
      "pmRaMasYr": -55.3,
      "pmDecMasYr": 7.48,
      "parallaxMas": 8.89,
      "mag": 6.31,
      "colorIndex": 1.156,
      "tier": "T1"
    },
    {
      "id": "hip-45437",
      "sourceId": "HIP 45437",
      "raDeg": 138.89471,
      "decDeg": -57.577762,
      "pmRaMasYr": -15.37,
      "pmDecMasYr": 8.32,
      "parallaxMas": 2.97,
      "mag": 6.32,
      "colorIndex": 1.037,
      "tier": "T1"
    },
    {
      "id": "hip-52526",
      "sourceId": "HIP 52526",
      "raDeg": 161.095496,
      "decDeg": -59.993327,
      "pmRaMasYr": -7.1,
      "pmDecMasYr": 2.48,
      "parallaxMas": 1.23,
      "mag": 6.32,
      "colorIndex": -0.31,
      "tier": "T1"
    },
    {
      "id": "hip-56961",
      "sourceId": "HIP 56961",
      "raDeg": 175.15421,
      "decDeg": -62.568103,
      "pmRaMasYr": -5.73,
      "pmDecMasYr": 0.61,
      "parallaxMas": 1.16,
      "mag": 6.32,
      "colorIndex": 0.029,
      "tier": "T1"
    },
    {
      "id": "hip-45603",
      "sourceId": "HIP 45603",
      "raDeg": 139.426286,
      "decDeg": -54.494857,
      "pmRaMasYr": -22.56,
      "pmDecMasYr": 11.83,
      "parallaxMas": 4.02,
      "mag": 6.33,
      "colorIndex": 1.403,
      "tier": "T1"
    },
    {
      "id": "hip-47591",
      "sourceId": "HIP 47591",
      "raDeg": 145.554114,
      "decDeg": -66.91482,
      "pmRaMasYr": -14.5,
      "pmDecMasYr": -0.26,
      "parallaxMas": 5.51,
      "mag": 6.33,
      "colorIndex": 0.075,
      "tier": "T1"
    },
    {
      "id": "hip-52160",
      "sourceId": "HIP 52160",
      "raDeg": 159.845227,
      "decDeg": -64.111813,
      "pmRaMasYr": -16.97,
      "pmDecMasYr": 10.2,
      "parallaxMas": 6.8,
      "mag": 6.33,
      "colorIndex": -0.072,
      "tier": "T1"
    },
    {
      "id": "hip-50785",
      "sourceId": "HIP 50785",
      "raDeg": 155.543649,
      "decDeg": -58.265637,
      "pmRaMasYr": -48.3,
      "pmDecMasYr": 26.72,
      "parallaxMas": 9.51,
      "mag": 6.34,
      "colorIndex": 0.884,
      "tier": "T1"
    },
    {
      "id": "hip-50916",
      "sourceId": "HIP 50916",
      "raDeg": 155.961065,
      "decDeg": -57.953904,
      "pmRaMasYr": -21.89,
      "pmDecMasYr": -11.86,
      "parallaxMas": 4.11,
      "mag": 6.34,
      "colorIndex": 1.517,
      "tier": "T1"
    },
    {
      "id": "hip-58469",
      "sourceId": "HIP 58469",
      "raDeg": 179.856773,
      "decDeg": -62.83095,
      "pmRaMasYr": -5.51,
      "pmDecMasYr": 0.91,
      "parallaxMas": -0.36,
      "mag": 6.34,
      "colorIndex": 0.317,
      "tier": "T1"
    },
    {
      "id": "hip-50562",
      "sourceId": "HIP 50562",
      "raDeg": 154.925175,
      "decDeg": -65.137244,
      "pmRaMasYr": -8.43,
      "pmDecMasYr": 2.13,
      "parallaxMas": 1.63,
      "mag": 6.35,
      "colorIndex": 1.556,
      "tier": "T1"
    },
    {
      "id": "hip-52308",
      "sourceId": "HIP 52308",
      "raDeg": 160.32302,
      "decDeg": -59.676922,
      "pmRaMasYr": -7.81,
      "pmDecMasYr": 2.58,
      "parallaxMas": 0.61,
      "mag": 6.35,
      "colorIndex": 0.088,
      "tier": "T1"
    },
    {
      "id": "hip-45214",
      "sourceId": "HIP 45214",
      "raDeg": 138.210972,
      "decDeg": -60.916815,
      "pmRaMasYr": -22.14,
      "pmDecMasYr": 18.93,
      "parallaxMas": 5.9,
      "mag": 6.36,
      "colorIndex": -0.044,
      "tier": "T1"
    },
    {
      "id": "hip-53589",
      "sourceId": "HIP 53589",
      "raDeg": 164.450807,
      "decDeg": -59.732195,
      "pmRaMasYr": -5.12,
      "pmDecMasYr": 2.09,
      "parallaxMas": -0.04,
      "mag": 6.36,
      "colorIndex": 0.84,
      "tier": "T1"
    },
    {
      "id": "hip-58452",
      "sourceId": "HIP 58452",
      "raDeg": 179.794607,
      "decDeg": -45.8322,
      "pmRaMasYr": -30.05,
      "pmDecMasYr": -8.45,
      "parallaxMas": 6.69,
      "mag": 6.36,
      "colorIndex": -0.081,
      "tier": "T1"
    },
    {
      "id": "hip-44665",
      "sourceId": "HIP 44665",
      "raDeg": 136.531708,
      "decDeg": -64.499921,
      "pmRaMasYr": 18.6,
      "pmDecMasYr": 29.57,
      "parallaxMas": 5.53,
      "mag": 6.37,
      "colorIndex": 1.361,
      "tier": "T1"
    },
    {
      "id": "hip-58085",
      "sourceId": "HIP 58085",
      "raDeg": 178.685908,
      "decDeg": -66.376039,
      "pmRaMasYr": 14.51,
      "pmDecMasYr": -65.43,
      "parallaxMas": 23.09,
      "mag": 6.38,
      "colorIndex": 0.406,
      "tier": "T1"
    },
    {
      "id": "hip-44423",
      "sourceId": "HIP 44423",
      "raDeg": 135.772299,
      "decDeg": -53.550395,
      "pmRaMasYr": -19.3,
      "pmDecMasYr": 9.42,
      "parallaxMas": 3.78,
      "mag": 6.39,
      "colorIndex": -0.074,
      "tier": "T1"
    },
    {
      "id": "hip-48730",
      "sourceId": "HIP 48730",
      "raDeg": 149.091257,
      "decDeg": -51.336154,
      "pmRaMasYr": -7.61,
      "pmDecMasYr": -1.66,
      "parallaxMas": 0.7,
      "mag": 6.39,
      "colorIndex": -0.162,
      "tier": "T1"
    },
    {
      "id": "hip-54289",
      "sourceId": "HIP 54289",
      "raDeg": 166.601331,
      "decDeg": -64.839956,
      "pmRaMasYr": -48.91,
      "pmDecMasYr": -6.73,
      "parallaxMas": 6.89,
      "mag": 6.39,
      "colorIndex": 0.114,
      "tier": "T1"
    },
    {
      "id": "hip-47422",
      "sourceId": "HIP 47422",
      "raDeg": 144.938121,
      "decDeg": -62.942969,
      "pmRaMasYr": -17.74,
      "pmDecMasYr": 18.53,
      "parallaxMas": 5.23,
      "mag": 6.4,
      "colorIndex": -0.084,
      "tier": "T1"
    },
    {
      "id": "hip-49619",
      "sourceId": "HIP 49619",
      "raDeg": 151.898875,
      "decDeg": -48.26083,
      "pmRaMasYr": -15.94,
      "pmDecMasYr": 3.94,
      "parallaxMas": 2.51,
      "mag": 6.4,
      "colorIndex": -0.15,
      "tier": "T1"
    },
    {
      "id": "hip-49223",
      "sourceId": "HIP 49223",
      "raDeg": 150.705929,
      "decDeg": -62.156676,
      "pmRaMasYr": -8.77,
      "pmDecMasYr": 3.89,
      "parallaxMas": 1.18,
      "mag": 6.41,
      "colorIndex": 1.688,
      "tier": "T1"
    },
    {
      "id": "hip-51461",
      "sourceId": "HIP 51461",
      "raDeg": 157.663511,
      "decDeg": -61.356507,
      "pmRaMasYr": 3.05,
      "pmDecMasYr": 13.36,
      "parallaxMas": 4.02,
      "mag": 6.41,
      "colorIndex": 1.65,
      "tier": "T1"
    },
    {
      "id": "hip-49092",
      "sourceId": "HIP 49092",
      "raDeg": 150.300062,
      "decDeg": -56.096562,
      "pmRaMasYr": -27.45,
      "pmDecMasYr": 1.0,
      "parallaxMas": 3.76,
      "mag": 6.42,
      "colorIndex": -0.013,
      "tier": "T1"
    },
    {
      "id": "hip-50067",
      "sourceId": "HIP 50067",
      "raDeg": 153.338331,
      "decDeg": -61.658836,
      "pmRaMasYr": -15.79,
      "pmDecMasYr": 2.73,
      "parallaxMas": 3.19,
      "mag": 6.42,
      "colorIndex": -0.111,
      "tier": "T1"
    },
    {
      "id": "hip-51265",
      "sourceId": "HIP 51265",
      "raDeg": 157.076174,
      "decDeg": -63.164573,
      "pmRaMasYr": -16.31,
      "pmDecMasYr": 3.26,
      "parallaxMas": 1.6,
      "mag": 6.42,
      "colorIndex": -0.039,
      "tier": "T1"
    },
    {
      "id": "hip-51327",
      "sourceId": "HIP 51327",
      "raDeg": 157.265297,
      "decDeg": -65.176335,
      "pmRaMasYr": 54.4,
      "pmDecMasYr": 37.44,
      "parallaxMas": 5.2,
      "mag": 6.42,
      "colorIndex": 1.675,
      "tier": "T1"
    },
    {
      "id": "hip-55003",
      "sourceId": "HIP 55003",
      "raDeg": 168.928181,
      "decDeg": -57.355869,
      "pmRaMasYr": -13.26,
      "pmDecMasYr": -5.41,
      "parallaxMas": 5.59,
      "mag": 6.42,
      "colorIndex": 0.098,
      "tier": "T1"
    },
    {
      "id": "hip-44565",
      "sourceId": "HIP 44565",
      "raDeg": 136.199981,
      "decDeg": -57.852629,
      "pmRaMasYr": -25.03,
      "pmDecMasYr": 22.71,
      "parallaxMas": 2.96,
      "mag": 6.43,
      "colorIndex": 0.288,
      "tier": "T1"
    },
    {
      "id": "hip-51984",
      "sourceId": "HIP 51984",
      "raDeg": 159.317183,
      "decDeg": -53.855265,
      "pmRaMasYr": -10.86,
      "pmDecMasYr": 2.15,
      "parallaxMas": 1.97,
      "mag": 6.43,
      "colorIndex": -0.15,
      "tier": "T1"
    },
    {
      "id": "hip-53811",
      "sourceId": "HIP 53811",
      "raDeg": 165.151385,
      "decDeg": -53.111869,
      "pmRaMasYr": -86.03,
      "pmDecMasYr": 15.35,
      "parallaxMas": 7.86,
      "mag": 6.44,
      "colorIndex": 1.28,
      "tier": "T1"
    },
    {
      "id": "hip-54380",
      "sourceId": "HIP 54380",
      "raDeg": 166.892271,
      "decDeg": -48.640038,
      "pmRaMasYr": -15.22,
      "pmDecMasYr": 23.14,
      "parallaxMas": 5.89,
      "mag": 6.44,
      "colorIndex": 1.486,
      "tier": "T1"
    },
    {
      "id": "hip-49642",
      "sourceId": "HIP 49642",
      "raDeg": 151.985988,
      "decDeg": -62.221435,
      "pmRaMasYr": -5.93,
      "pmDecMasYr": 7.81,
      "parallaxMas": 3.99,
      "mag": 6.45,
      "colorIndex": -0.095,
      "tier": "T1"
    },
    {
      "id": "hip-52488",
      "sourceId": "HIP 52488",
      "raDeg": 160.967773,
      "decDeg": -60.117788,
      "pmRaMasYr": -6.55,
      "pmDecMasYr": 2.03,
      "parallaxMas": 0.5,
      "mag": 6.45,
      "colorIndex": -0.017,
      "tier": "T1"
    },
    {
      "id": "hip-53260",
      "sourceId": "HIP 53260",
      "raDeg": 163.389263,
      "decDeg": -56.420513,
      "pmRaMasYr": -17.46,
      "pmDecMasYr": 5.19,
      "parallaxMas": 0.03,
      "mag": 6.45,
      "colorIndex": 1.392,
      "tier": "T1"
    },
    {
      "id": "hip-56050",
      "sourceId": "HIP 56050",
      "raDeg": 172.3131,
      "decDeg": -63.553941,
      "pmRaMasYr": -6.26,
      "pmDecMasYr": 1.29,
      "parallaxMas": 0.66,
      "mag": 6.45,
      "colorIndex": 0.32,
      "tier": "T1"
    },
    {
      "id": "hip-44509",
      "sourceId": "HIP 44509",
      "raDeg": 136.024124,
      "decDeg": -47.441464,
      "pmRaMasYr": -11.1,
      "pmDecMasYr": 5.72,
      "parallaxMas": 2.85,
      "mag": 6.46,
      "colorIndex": -0.155,
      "tier": "T1"
    },
    {
      "id": "hip-52815",
      "sourceId": "HIP 52815",
      "raDeg": 161.973126,
      "decDeg": -64.262866,
      "pmRaMasYr": -15.46,
      "pmDecMasYr": 9.65,
      "parallaxMas": 6.95,
      "mag": 6.46,
      "colorIndex": 0.008,
      "tier": "T1"
    },
    {
      "id": "hip-56769",
      "sourceId": "HIP 56769",
      "raDeg": 174.584876,
      "decDeg": -63.372751,
      "pmRaMasYr": -6.24,
      "pmDecMasYr": 1.49,
      "parallaxMas": -1.44,
      "mag": 6.46,
      "colorIndex": 0.043,
      "tier": "T1"
    },
    {
      "id": "hip-47893",
      "sourceId": "HIP 47893",
      "raDeg": 146.419329,
      "decDeg": -57.18606,
      "pmRaMasYr": -18.69,
      "pmDecMasYr": 7.75,
      "parallaxMas": 3.75,
      "mag": 6.47,
      "colorIndex": -0.108,
      "tier": "T1"
    },
    {
      "id": "hip-52806",
      "sourceId": "HIP 52806",
      "raDeg": 161.93473,
      "decDeg": -59.875257,
      "pmRaMasYr": -15.53,
      "pmDecMasYr": -0.12,
      "parallaxMas": 2.65,
      "mag": 6.47,
      "colorIndex": -0.121,
      "tier": "T1"
    },
    {
      "id": "hip-44979",
      "sourceId": "HIP 44979",
      "raDeg": 137.437486,
      "decDeg": -49.424314,
      "pmRaMasYr": -0.21,
      "pmDecMasYr": -28.74,
      "parallaxMas": 6.35,
      "mag": 6.48,
      "colorIndex": 0.17,
      "tier": "T1"
    },
    {
      "id": "hip-50069",
      "sourceId": "HIP 50069",
      "raDeg": 153.342985,
      "decDeg": -56.586699,
      "pmRaMasYr": -26.39,
      "pmDecMasYr": 0.61,
      "parallaxMas": 3.97,
      "mag": 6.48,
      "colorIndex": 1.45,
      "tier": "T1"
    },
    {
      "id": "hip-50391",
      "sourceId": "HIP 50391",
      "raDeg": 154.334171,
      "decDeg": -46.834943,
      "pmRaMasYr": -22.66,
      "pmDecMasYr": 0.45,
      "parallaxMas": 16.07,
      "mag": 6.48,
      "colorIndex": 0.329,
      "tier": "T1"
    },
    {
      "id": "hip-48469",
      "sourceId": "HIP 48469",
      "raDeg": 148.250438,
      "decDeg": -55.373217,
      "pmRaMasYr": -12.65,
      "pmDecMasYr": 3.72,
      "parallaxMas": 0.46,
      "mag": 6.5,
      "colorIndex": -0.145,
      "tier": "T1"
    },
    {
      "id": "hip-49052",
      "sourceId": "HIP 49052",
      "raDeg": 150.144091,
      "decDeg": -56.946165,
      "pmRaMasYr": -53.08,
      "pmDecMasYr": 23.35,
      "parallaxMas": 6.38,
      "mag": 6.5,
      "colorIndex": 0.979,
      "tier": "T1"
    },
    {
      "id": "hip-49477",
      "sourceId": "HIP 49477",
      "raDeg": 151.530265,
      "decDeg": -52.187978,
      "pmRaMasYr": -55.35,
      "pmDecMasYr": 16.15,
      "parallaxMas": 8.28,
      "mag": 6.5,
      "colorIndex": 0.997,
      "tier": "T1"
    },
    {
      "id": "hip-52103",
      "sourceId": "HIP 52103",
      "raDeg": 159.689143,
      "decDeg": -59.26242,
      "pmRaMasYr": -14.26,
      "pmDecMasYr": -0.18,
      "parallaxMas": 2.17,
      "mag": 6.5,
      "colorIndex": -0.098,
      "tier": "T1"
    },
    {
      "id": "hip-55645",
      "sourceId": "HIP 55645",
      "raDeg": 170.985599,
      "decDeg": -57.880394,
      "pmRaMasYr": 10.9,
      "pmDecMasYr": -17.88,
      "parallaxMas": 5.81,
      "mag": 6.5,
      "colorIndex": 1.504,
      "tier": "T1"
    }
  ],
  "labelCandidates": [],
  "provenance": {
    "catalog": "hipparcos",
    "sourcePath": "/home/rocco/Astronomy-Hub/data/sky-engine/hipparcos/source/hip_main.dat",
    "generator": "scripts/sky-engine/build_hipparcos_tiles.py",
    "generatedAt": "2026-04-07T01:17:31.778592Z",
    "sourceRecordCount": 8870,
    "tierSet": [
      "T0",
      "T1"
    ]
  }
}