{
  "tileId": "root-sw-sw-se-sw",
  "level": 3,
  "parentTileId": "root-sw-sw-se",
  "childTileIds": [],
  "bounds": {
    "raMinDeg": 45.0,
    "raMaxDeg": 67.5,
    "decMinDeg": -90,
    "decMaxDeg": -78.75
  },
  "magMin": 5.67,
  "magMax": 6.4,
  "starCount": 4,
  "stars": [
    {
      "id": "hip-14521",
      "sourceId": "HIP 14521",
      "raDeg": 46.88292,
      "decDeg": -78.989423,
      "pmRaMasYr": 79.07,
      "pmDecMasYr": 73.56,
      "parallaxMas": 13.13,
      "mag": 5.67,
      "colorIndex": 0.298,
      "tier": "T1"
    },
    {
      "id": "hip-20049",
      "sourceId": "HIP 20049",
      "raDeg": 64.496569,
      "decDeg": -80.214181,
      "pmRaMasYr": 28.26,
      "pmDecMasYr": 61.02,
      "parallaxMas": 8.0,
      "mag": 5.67,
      "colorIndex": 0.836,
      "tier": "T1"
    },
    {
      "id": "hip-20297",
      "sourceId": "HIP 20297",
      "raDeg": 65.241798,
      "decDeg": -81.580227,
      "pmRaMasYr": 9.07,
      "pmDecMasYr": 126.08,
      "parallaxMas": 18.61,
      "mag": 5.78,
      "colorIndex": 0.359,
      "tier": "T1"
    },
    {
      "id": "hip-17328",
      "sourceId": "HIP 17328",
      "raDeg": 55.636208,
      "decDeg": -85.262023,
      "pmRaMasYr": 20.99,
      "pmDecMasYr": 24.32,
      "parallaxMas": 6.78,
      "mag": 6.4,
      "colorIndex": -0.005,
      "tier": "T1"
    }
  ],
  "labelCandidates": [],
  "provenance": {
    "catalog": "hipparcos",
    "sourcePath": "/home/rocco/Astronomy-Hub/data/sky-engine/hipparcos/source/hip_main.dat",
    "generator": "scripts/sky-engine/build_hipparcos_tiles.py",
    "generatedAt": "2026-04-07T01:17:31.778592Z",
    "sourceRecordCount": 8870,
    "tierSet": [
      "T1"
    ]
  }
}